{"resonator_template": {"id": "[腦測]+0布蘭特+1不滅航路,+6散華+1赫奕流明,+0維里奈+1奇幻變奏-熔山-250共效", "labels": [{"name": "", "duration_1": "", "duration_2": ""}], "test_resonator_id_1": "", "test_resonator_id_2": "", "test_resonator_id_3": "", "duration_1": "25", "duration_2": "26", "monster_id": "90等抗性20白板", "description": "https://www.youtube.com/watch?v=9KIKkAA4pd4", "resonators": [{"resonator_name": "布蘭特", "resonator_chain": "0", "resonator_weapon_name": "不滅航路", "resonator_weapon_rank": "1", "resonator_inherent_skill_1": true, "resonator_inherent_skill_2": true, "resonator_base_attr": "攻擊", "resonator_skill_bonus": "普攻", "resonator_energy_regen": "250.00%", "resonator_echo_1": "夢魘·燎照之騎", "resonator_echo_sonata_1": "熔山裂谷", "resonator_echo_sonata_2": "熔山裂谷", "resonator_echo_sonata_3": "熔山裂谷", "resonator_echo_sonata_4": "熔山裂谷", "resonator_echo_sonata_5": "熔山裂谷", "resonator_echo_cost_1": "4", "resonator_echo_cost_2": "3", "resonator_echo_cost_3": "3", "resonator_echo_cost_4": "1", "resonator_echo_cost_5": "1", "resonator_echo_affix_1": "暴傷", "resonator_echo_affix_2": "共效", "resonator_echo_affix_3": "熱熔", "resonator_echo_affix_4": "攻", "resonator_echo_affix_5": "攻"}, {"resonator_name": "散華", "resonator_chain": "6", "resonator_weapon_name": "赫奕流明", "resonator_weapon_rank": "1", "resonator_inherent_skill_1": true, "resonator_inherent_skill_2": true, "resonator_base_attr": "攻擊", "resonator_skill_bonus": "共鳴技能", "resonator_energy_regen": "", "resonator_echo_1": "無常凶鷺", "resonator_echo_sonata_1": "輕雲出月", "resonator_echo_sonata_2": "輕雲出月", "resonator_echo_sonata_3": "輕雲出月", "resonator_echo_sonata_4": "輕雲出月", "resonator_echo_sonata_5": "輕雲出月", "resonator_echo_cost_1": "", "resonator_echo_cost_2": "", "resonator_echo_cost_3": "", "resonator_echo_cost_4": "", "resonator_echo_cost_5": "", "resonator_echo_affix_1": "", "resonator_echo_affix_2": "", "resonator_echo_affix_3": "", "resonator_echo_affix_4": "", "resonator_echo_affix_5": ""}, {"resonator_name": "維里奈", "resonator_chain": "0", "resonator_weapon_name": "奇幻變奏", "resonator_weapon_rank": "1", "resonator_inherent_skill_1": true, "resonator_inherent_skill_2": true, "resonator_base_attr": "攻擊", "resonator_skill_bonus": "普攻", "resonator_energy_regen": "", "resonator_echo_1": "鳴鐘之龜", "resonator_echo_sonata_1": "隱世回光", "resonator_echo_sonata_2": "隱世回光", "resonator_echo_sonata_3": "隱世回光", "resonator_echo_sonata_4": "隱世回光", "resonator_echo_sonata_5": "隱世回光", "resonator_echo_cost_1": "", "resonator_echo_cost_2": "", "resonator_echo_cost_3": "", "resonator_echo_cost_4": "", "resonator_echo_cost_5": "", "resonator_echo_affix_1": "", "resonator_echo_affix_2": "", "resonator_echo_affix_3": "", "resonator_echo_affix_4": "", "resonator_echo_affix_5": ""}], "rows": [{"labels": [], "resonator_name": "布蘭特", "real_dmg_no_crit": "", "real_dmg_crit": "", "action": "無", "skill_id": "", "skill_bonus_type": "", "hit": "1", "buffs": [], "resonating_spin_concerto_regen": "", "accumulated_resonating_spin_concerto_regen": "", "time_start": "", "time_end": "", "cumulative_time": "", "frame": "", "comment": ""}, {"labels": [], "resonator_name": "散華", "real_dmg_no_crit": "", "real_dmg_crit": "", "action": "入場", "skill_id": "", "skill_bonus_type": "", "hit": "1", "buffs": [], "resonating_spin_concerto_regen": "", "accumulated_resonating_spin_concerto_regen": "", "time_start": "", "time_end": "", "cumulative_time": "", "frame": "", "comment": ""}, {"labels": [], "resonator_name": "散華", "real_dmg_no_crit": "", "real_dmg_crit": "", "action": "共鳴技能", "skill_id": "朔雪永凍", "skill_bonus_type": "", "hit": "1", "buffs": [{"name": "[共鳴技能]赫奕流明-1諧振-灼羽", "type": "加成", "value": "0.04", "stack": "5", "duration": ""}], "resonating_spin_concerto_regen": "", "accumulated_resonating_spin_concerto_regen": "", "time_start": "00:00:59", "time_end": "", "cumulative_time": "", "frame": "", "comment": ""}, {"labels": [], "resonator_name": "散華", "real_dmg_no_crit": "", "real_dmg_crit": "", "action": "共鳴解放", "skill_id": "焦瞑凍土", "skill_bonus_type": "", "hit": "1", "buffs": [], "resonating_spin_concerto_regen": "", "accumulated_resonating_spin_concerto_regen": "", "time_start": "00:00:89", "time_end": "00:00:91", "cumulative_time": "", "frame": "", "comment": ""}, {"labels": [], "resonator_name": "散華", "real_dmg_no_crit": "", "real_dmg_crit": "", "action": "重擊", "skill_id": "爆裂傷害-1", "skill_bonus_type": "", "hit": "1", "buffs": [{"name": "[加成-自己]散華-共鳴鏈4-劍修五蘊", "type": "加成", "value": "1.2", "stack": "1", "duration": "5"}], "resonating_spin_concerto_regen": "", "accumulated_resonating_spin_concerto_regen": "", "time_start": "", "time_end": "", "cumulative_time": "", "frame": "", "comment": ""}, {"labels": [], "resonator_name": "散華", "real_dmg_no_crit": "", "real_dmg_crit": "", "action": "", "skill_id": "冰棱爆炸傷害", "skill_bonus_type": "", "hit": "1", "buffs": [{"name": "[共鳴技能]赫奕流明-1諧振-灼羽", "type": "加成", "value": "0.04", "stack": "7", "duration": ""}, {"name": "[暴擊傷害-自己]散華-共鳴鏈5-顛覆無常", "type": "暴擊傷害", "value": "1.0", "stack": "1", "duration": ""}], "resonating_spin_concerto_regen": "", "accumulated_resonating_spin_concerto_regen": "", "time_start": "", "time_end": "", "cumulative_time": "", "frame": "", "comment": ""}, {"labels": [], "resonator_name": "散華", "real_dmg_no_crit": "", "real_dmg_crit": "", "action": "", "skill_id": "冰川爆炸傷害", "skill_bonus_type": "", "hit": "1", "buffs": [{"name": "[共鳴技能]赫奕流明-1諧振-灼羽", "type": "加成", "value": "0.04", "stack": "7", "duration": ""}, {"name": "[攻擊百分比-全部]散華-共鳴鏈6-曙色天光", "type": "攻擊百分比", "value": "0.1", "stack": "2", "duration": "20"}, {"name": "[暴擊傷害-自己]散華-共鳴鏈5-顛覆無常", "type": "暴擊傷害", "value": "1.0", "stack": "1", "duration": ""}], "resonating_spin_concerto_regen": "", "accumulated_resonating_spin_concerto_regen": "", "time_start": "", "time_end": "", "cumulative_time": "", "frame": "", "comment": ""}, {"labels": [], "resonator_name": "散華", "real_dmg_no_crit": "", "real_dmg_crit": "", "action": "", "skill_id": "冰川爆炸傷害", "skill_bonus_type": "", "hit": "1", "buffs": [{"name": "[共鳴技能]赫奕流明-1諧振-灼羽", "type": "加成", "value": "0.04", "stack": "7", "duration": ""}, {"name": "[攻擊百分比-全部]散華-共鳴鏈6-曙色天光", "type": "攻擊百分比", "value": "0.1", "stack": "2", "duration": "20"}, {"name": "[暴擊傷害-自己]散華-共鳴鏈5-顛覆無常", "type": "暴擊傷害", "value": "1.0", "stack": "1", "duration": ""}], "resonating_spin_concerto_regen": "", "accumulated_resonating_spin_concerto_regen": "", "time_start": "", "time_end": "", "cumulative_time": "", "frame": "", "comment": ""}, {"labels": [], "resonator_name": "散華", "real_dmg_no_crit": "", "real_dmg_crit": "", "action": "", "skill_id": "爆裂傷害-1", "skill_bonus_type": "", "hit": "1", "buffs": [{"name": "[加成-自己]散華-共鳴鏈4-劍修五蘊", "type": "加成", "value": "1.2", "stack": "1", "duration": "5"}, {"name": "[攻擊百分比-全部]散華-共鳴鏈6-曙色天光", "type": "攻擊百分比", "value": "0.1", "stack": "2", "duration": "20"}], "resonating_spin_concerto_regen": "", "accumulated_resonating_spin_concerto_regen": "", "time_start": "", "time_end": "00:02:56", "cumulative_time": "", "frame": "", "comment": ""}, {"labels": [], "resonator_name": "維里奈", "real_dmg_no_crit": "", "real_dmg_crit": "", "action": "入場", "skill_id": "第三段傷害", "skill_bonus_type": "", "hit": "1", "buffs": [], "resonating_spin_concerto_regen": "", "accumulated_resonating_spin_concerto_regen": "", "time_start": "00:01:30", "time_end": "", "cumulative_time": "", "frame": "", "comment": ""}, {"labels": [], "resonator_name": "維里奈", "real_dmg_no_crit": "", "real_dmg_crit": "", "action": "普攻", "skill_id": "第四段傷害", "skill_bonus_type": "", "hit": "1", "buffs": [], "resonating_spin_concerto_regen": "", "accumulated_resonating_spin_concerto_regen": "", "time_start": "", "time_end": "", "cumulative_time": "", "frame": "", "comment": ""}, {"labels": [], "resonator_name": "維里奈", "real_dmg_no_crit": "", "real_dmg_crit": "", "action": "普攻", "skill_id": "第五段傷害", "skill_bonus_type": "", "hit": "1", "buffs": [{"name": "[攻擊百分比-全部]散華-共鳴鏈6-曙色天光", "type": "攻擊百分比", "value": "0.1", "stack": "2", "duration": "20"}], "resonating_spin_concerto_regen": "", "accumulated_resonating_spin_concerto_regen": "", "time_start": "", "time_end": "", "cumulative_time": "", "frame": "", "comment": ""}, {"labels": [], "resonator_name": "維里奈", "real_dmg_no_crit": "", "real_dmg_crit": "", "action": "共鳴解放", "skill_id": "草木生長", "skill_bonus_type": "", "hit": "1", "buffs": [{"name": "[攻擊百分比-全部]散華-共鳴鏈6-曙色天光", "type": "攻擊百分比", "value": "0.1", "stack": "2", "duration": "20"}, {"name": "[攻擊百分比-全部]維里奈-固有技能1-自然的獻禮", "type": "攻擊百分比", "value": "0.2", "stack": "1", "duration": "20"}], "resonating_spin_concerto_regen": "", "accumulated_resonating_spin_concerto_regen": "", "time_start": "00:03:09", "time_end": "00:03:65", "cumulative_time": "", "frame": "", "comment": ""}, {"labels": [], "resonator_name": "維里奈", "real_dmg_no_crit": "", "real_dmg_crit": "", "action": "共鳴技能", "skill_id": "", "skill_bonus_type": "", "hit": "1", "buffs": [], "resonating_spin_concerto_regen": "", "accumulated_resonating_spin_concerto_regen": "", "time_start": "00:03:95", "time_end": "", "cumulative_time": "", "frame": "", "comment": ""}, {"labels": [], "resonator_name": "維里奈", "real_dmg_no_crit": "", "real_dmg_crit": "", "action": "聲骸", "skill_id": "五星 鳴鐘之龜", "skill_bonus_type": "", "hit": "1", "buffs": [{"name": "[加成-全部]鳴鐘之龜", "type": "加成", "value": "0.1", "stack": "1", "duration": "15"}], "resonating_spin_concerto_regen": "", "accumulated_resonating_spin_concerto_regen": "", "time_start": "00:04:03", "time_end": "", "cumulative_time": "", "frame": "", "comment": ""}, {"labels": [], "resonator_name": "維里奈", "real_dmg_no_crit": "", "real_dmg_crit": "", "action": "跳", "skill_id": "", "skill_bonus_type": "", "hit": "1", "buffs": [], "resonating_spin_concerto_regen": "", "accumulated_resonating_spin_concerto_regen": "", "time_start": "", "time_end": "", "cumulative_time": "", "frame": "", "comment": ""}, {"labels": [], "resonator_name": "維里奈", "real_dmg_no_crit": "", "real_dmg_crit": "", "action": "空中攻擊", "skill_id": "空中攻擊·星星花綻放第一段傷害", "skill_bonus_type": "", "hit": "1", "buffs": [{"name": "[加成-全部]鳴鐘之龜", "type": "加成", "value": "0.1", "stack": "1", "duration": "15"}, {"name": "[攻擊百分比-全部]散華-共鳴鏈6-曙色天光", "type": "攻擊百分比", "value": "0.1", "stack": "2", "duration": "20"}, {"name": "[攻擊百分比-全部]維里奈-固有技能1-自然的獻禮", "type": "攻擊百分比", "value": "0.2", "stack": "1", "duration": "20"}, {"name": "[攻擊百分比-全部]隱世回光-5/5", "type": "攻擊百分比", "value": "0.15", "stack": "1", "duration": "30"}], "resonating_spin_concerto_regen": "", "accumulated_resonating_spin_concerto_regen": "", "time_start": "", "time_end": "", "cumulative_time": "", "frame": "", "comment": ""}, {"labels": [], "resonator_name": "維里奈", "real_dmg_no_crit": "", "real_dmg_crit": "", "action": "空中攻擊", "skill_id": "空中攻擊·星星花綻放第二段傷害", "skill_bonus_type": "", "hit": "1", "buffs": [{"name": "[加成-全部]鳴鐘之龜", "type": "加成", "value": "0.1", "stack": "1", "duration": "15"}, {"name": "[攻擊百分比-全部]散華-共鳴鏈6-曙色天光", "type": "攻擊百分比", "value": "0.1", "stack": "2", "duration": "20"}, {"name": "[攻擊百分比-全部]維里奈-固有技能1-自然的獻禮", "type": "攻擊百分比", "value": "0.2", "stack": "1", "duration": "20"}, {"name": "[攻擊百分比-全部]隱世回光-5/5", "type": "攻擊百分比", "value": "0.15", "stack": "1", "duration": "30"}], "resonating_spin_concerto_regen": "", "accumulated_resonating_spin_concerto_regen": "", "time_start": "", "time_end": "", "cumulative_time": "", "frame": "", "comment": ""}, {"labels": [], "resonator_name": "維里奈", "real_dmg_no_crit": "", "real_dmg_crit": "", "action": "延奏", "skill_id": "", "skill_bonus_type": "", "hit": "1", "buffs": [], "resonating_spin_concerto_regen": "", "accumulated_resonating_spin_concerto_regen": "", "time_start": "", "time_end": "", "cumulative_time": "", "frame": "", "comment": ""}, {"labels": [], "resonator_name": "布蘭特", "real_dmg_no_crit": "", "real_dmg_crit": "", "action": "變奏", "skill_id": "為我！", "skill_bonus_type": "", "hit": "1", "buffs": [{"name": "[加成-全部]鳴鐘之龜", "type": "加成", "value": "0.1", "stack": "1", "duration": "15"}, {"name": "[加深-全部]維里奈-延奏技能-盛放", "type": "加深", "value": "0.15", "stack": "1", "duration": "30"}, {"name": "[攻擊-自己]布蘭特-共鳴回路-戲中人生", "type": "攻擊", "value": "1200", "stack": "1", "duration": ""}, {"name": "[攻擊百分比-全部]散華-共鳴鏈6-曙色天光", "type": "攻擊百分比", "value": "0.1", "stack": "2", "duration": "20"}, {"name": "[攻擊百分比-全部]維里奈-固有技能1-自然的獻禮", "type": "攻擊百分比", "value": "0.2", "stack": "1", "duration": "20"}, {"name": "[攻擊百分比-全部]隱世回光-5/5", "type": "攻擊百分比", "value": "0.15", "stack": "1", "duration": "30"}], "resonating_spin_concerto_regen": "", "accumulated_resonating_spin_concerto_regen": "", "time_start": "00:05:16", "time_end": "", "cumulative_time": "", "frame": "", "comment": ""}, {"labels": [], "resonator_name": "布蘭特", "real_dmg_no_crit": "", "real_dmg_crit": "", "action": "重擊", "skill_id": "空中攻擊第二段長按傷害", "skill_bonus_type": "", "hit": "1", "buffs": [{"name": "[加成-全部]鳴鐘之龜", "type": "加成", "value": "0.1", "stack": "1", "duration": "15"}, {"name": "[加深-全部]維里奈-延奏技能-盛放", "type": "加深", "value": "0.15", "stack": "1", "duration": "30"}, {"name": "[攻擊-自己]布蘭特-共鳴回路-戲中人生", "type": "攻擊", "value": "1200", "stack": "1", "duration": ""}, {"name": "[攻擊百分比-全部]散華-共鳴鏈6-曙色天光", "type": "攻擊百分比", "value": "0.1", "stack": "2", "duration": "20"}, {"name": "[攻擊百分比-全部]維里奈-固有技能1-自然的獻禮", "type": "攻擊百分比", "value": "0.2", "stack": "1", "duration": "20"}, {"name": "[攻擊百分比-全部]隱世回光-5/5", "type": "攻擊百分比", "value": "0.15", "stack": "1", "duration": "30"}, {"name": "[普攻]不滅航路-1諧振-普攻傷害時", "type": "加成", "value": "0.24", "stack": "1", "duration": "4"}], "resonating_spin_concerto_regen": "", "accumulated_resonating_spin_concerto_regen": "", "time_start": "", "time_end": "", "cumulative_time": "", "frame": "", "comment": "布蘭特變奏之後直接重擊按著，等轉完圈，布蘭特後跳，接共鳴技能落地，就可以切人了。這邊打完應該有2/4能量。"}, {"labels": [], "resonator_name": "布蘭特", "real_dmg_no_crit": "", "real_dmg_crit": "", "action": "", "skill_id": "空中攻擊第二段空翻傷害", "skill_bonus_type": "", "hit": "1", "buffs": [{"name": "[加成-全部]鳴鐘之龜", "type": "加成", "value": "0.1", "stack": "1", "duration": "15"}, {"name": "[加深-全部]維里奈-延奏技能-盛放", "type": "加深", "value": "0.15", "stack": "1", "duration": "30"}, {"name": "[攻擊-自己]布蘭特-共鳴回路-戲中人生", "type": "攻擊", "value": "1200", "stack": "1", "duration": ""}, {"name": "[攻擊百分比-全部]散華-共鳴鏈6-曙色天光", "type": "攻擊百分比", "value": "0.1", "stack": "2", "duration": "20"}, {"name": "[攻擊百分比-全部]維里奈-固有技能1-自然的獻禮", "type": "攻擊百分比", "value": "0.2", "stack": "1", "duration": "20"}, {"name": "[攻擊百分比-全部]隱世回光-5/5", "type": "攻擊百分比", "value": "0.15", "stack": "1", "duration": "30"}, {"name": "[普攻]不滅航路-1諧振-普攻傷害時", "type": "加成", "value": "0.24", "stack": "1", "duration": "4"}], "resonating_spin_concerto_regen": "", "accumulated_resonating_spin_concerto_regen": "", "time_start": "", "time_end": "", "cumulative_time": "", "frame": "", "comment": ""}, {"labels": [], "resonator_name": "布蘭特", "real_dmg_no_crit": "", "real_dmg_crit": "", "action": "共鳴技能", "skill_id": "下落攻擊傷害", "skill_bonus_type": "", "hit": "1", "buffs": [{"name": "[加成-全部]鳴鐘之龜", "type": "加成", "value": "0.1", "stack": "1", "duration": "15"}, {"name": "[加深-全部]維里奈-延奏技能-盛放", "type": "加深", "value": "0.15", "stack": "1", "duration": "30"}, {"name": "[攻擊-自己]布蘭特-共鳴回路-戲中人生", "type": "攻擊", "value": "1200", "stack": "1", "duration": ""}, {"name": "[攻擊百分比-全部]散華-共鳴鏈6-曙色天光", "type": "攻擊百分比", "value": "0.1", "stack": "2", "duration": "20"}, {"name": "[攻擊百分比-全部]維里奈-固有技能1-自然的獻禮", "type": "攻擊百分比", "value": "0.2", "stack": "1", "duration": "20"}, {"name": "[攻擊百分比-全部]隱世回光-5/5", "type": "攻擊百分比", "value": "0.15", "stack": "1", "duration": "30"}, {"name": "[熱熔-自己]熔山裂谷-5/5", "type": "加成", "value": "0.3", "stack": "1", "duration": "15"}], "resonating_spin_concerto_regen": "", "accumulated_resonating_spin_concerto_regen": "", "time_start": "00:09:31", "time_end": "", "cumulative_time": "", "frame": "", "comment": ""}, {"labels": [], "resonator_name": "散華", "real_dmg_no_crit": "", "real_dmg_crit": "", "action": "入場", "skill_id": "第二段傷害", "skill_bonus_type": "", "hit": "1", "buffs": [{"name": "[加成-全部]鳴鐘之龜", "type": "加成", "value": "0.1", "stack": "1", "duration": "15"}, {"name": "[加深-全部]維里奈-延奏技能-盛放", "type": "加深", "value": "0.15", "stack": "1", "duration": "30"}, {"name": "[攻擊百分比-全部]散華-共鳴鏈6-曙色天光", "type": "攻擊百分比", "value": "0.1", "stack": "2", "duration": "20"}, {"name": "[攻擊百分比-全部]維里奈-固有技能1-自然的獻禮", "type": "攻擊百分比", "value": "0.2", "stack": "1", "duration": "20"}, {"name": "[攻擊百分比-全部]隱世回光-5/5", "type": "攻擊百分比", "value": "0.15", "stack": "1", "duration": "30"}], "resonating_spin_concerto_regen": "", "accumulated_resonating_spin_concerto_regen": "", "time_start": "00:10:16", "time_end": "", "cumulative_time": "", "frame": "", "comment": "散華平地入場。"}, {"labels": [], "resonator_name": "散華", "real_dmg_no_crit": "", "real_dmg_crit": "", "action": "共鳴技能", "skill_id": "朔雪永凍", "skill_bonus_type": "", "hit": "1", "buffs": [{"name": "[加成-全部]鳴鐘之龜", "type": "加成", "value": "0.1", "stack": "1", "duration": "15"}, {"name": "[加深-全部]維里奈-延奏技能-盛放", "type": "加深", "value": "0.15", "stack": "1", "duration": "30"}, {"name": "[攻擊百分比-全部]散華-共鳴鏈6-曙色天光", "type": "攻擊百分比", "value": "0.1", "stack": "2", "duration": "20"}, {"name": "[攻擊百分比-全部]維里奈-固有技能1-自然的獻禮", "type": "攻擊百分比", "value": "0.2", "stack": "1", "duration": "20"}, {"name": "[攻擊百分比-全部]隱世回光-5/5", "type": "攻擊百分比", "value": "0.15", "stack": "1", "duration": "30"}], "resonating_spin_concerto_regen": "", "accumulated_resonating_spin_concerto_regen": "", "time_start": "00:10:82", "time_end": "", "cumulative_time": "", "frame": "", "comment": ""}, {"labels": [], "resonator_name": "散華", "real_dmg_no_crit": "", "real_dmg_crit": "", "action": "聲骸", "skill_id": "五星 無常凶鷺-1", "skill_bonus_type": "", "hit": "1", "buffs": [{"name": "[加成-全部]鳴鐘之龜", "type": "加成", "value": "0.1", "stack": "1", "duration": "15"}, {"name": "[加深-全部]維里奈-延奏技能-盛放", "type": "加深", "value": "0.15", "stack": "1", "duration": "30"}, {"name": "[攻擊百分比-全部]散華-共鳴鏈6-曙色天光", "type": "攻擊百分比", "value": "0.1", "stack": "2", "duration": "20"}, {"name": "[攻擊百分比-全部]維里奈-固有技能1-自然的獻禮", "type": "攻擊百分比", "value": "0.2", "stack": "1", "duration": "20"}, {"name": "[攻擊百分比-全部]隱世回光-5/5", "type": "攻擊百分比", "value": "0.15", "stack": "1", "duration": "30"}], "resonating_spin_concerto_regen": "", "accumulated_resonating_spin_concerto_regen": "", "time_start": "00:11:12", "time_end": "", "cumulative_time": "", "frame": "", "comment": ""}, {"labels": [], "resonator_name": "散華", "real_dmg_no_crit": "", "real_dmg_crit": "", "action": "延奏", "skill_id": "", "skill_bonus_type": "", "hit": "1", "buffs": [], "resonating_spin_concerto_regen": "", "accumulated_resonating_spin_concerto_regen": "", "time_start": "", "time_end": "", "cumulative_time": "", "frame": "", "comment": ""}, {"labels": [], "resonator_name": "布蘭特", "real_dmg_no_crit": "", "real_dmg_crit": "", "action": "變奏", "skill_id": "為我！", "skill_bonus_type": "", "hit": "1", "buffs": [{"name": "[加成-下一位]無常凶鷺", "type": "加成", "value": "0.12", "stack": "1", "duration": "15"}, {"name": "[加成-全部]鳴鐘之龜", "type": "加成", "value": "0.1", "stack": "1", "duration": "15"}, {"name": "[加深-全部]維里奈-延奏技能-盛放", "type": "加深", "value": "0.15", "stack": "1", "duration": "30"}, {"name": "[攻擊-自己]布蘭特-共鳴回路-戲中人生", "type": "攻擊", "value": "1200", "stack": "1", "duration": ""}, {"name": "[攻擊百分比-全部]散華-共鳴鏈6-曙色天光", "type": "攻擊百分比", "value": "0.1", "stack": "2", "duration": "20"}, {"name": "[攻擊百分比-全部]維里奈-固有技能1-自然的獻禮", "type": "攻擊百分比", "value": "0.2", "stack": "1", "duration": "20"}, {"name": "[攻擊百分比-全部]隱世回光-5/5", "type": "攻擊百分比", "value": "0.15", "stack": "1", "duration": "30"}, {"name": "[熱熔-自己]熔山裂谷-5/5", "type": "加成", "value": "0.3", "stack": "1", "duration": "15"}], "resonating_spin_concerto_regen": "", "accumulated_resonating_spin_concerto_regen": "", "time_start": "00:11:43", "time_end": "", "cumulative_time": "", "frame": "", "comment": ""}, {"labels": [], "resonator_name": "布蘭特", "real_dmg_no_crit": "", "real_dmg_crit": "", "action": "重擊", "skill_id": "空中攻擊第二段長按傷害", "skill_bonus_type": "", "hit": "1", "buffs": [{"name": "[加成-下一位]無常凶鷺", "type": "加成", "value": "0.12", "stack": "1", "duration": "15"}, {"name": "[加成-全部]鳴鐘之龜", "type": "加成", "value": "0.1", "stack": "1", "duration": "15"}, {"name": "[加深-全部]維里奈-延奏技能-盛放", "type": "加深", "value": "0.15", "stack": "1", "duration": "30"}, {"name": "[攻擊-自己]布蘭特-共鳴回路-戲中人生", "type": "攻擊", "value": "1200", "stack": "1", "duration": ""}, {"name": "[攻擊百分比-全部]散華-共鳴鏈6-曙色天光", "type": "攻擊百分比", "value": "0.1", "stack": "2", "duration": "20"}, {"name": "[攻擊百分比-全部]維里奈-固有技能1-自然的獻禮", "type": "攻擊百分比", "value": "0.2", "stack": "1", "duration": "20"}, {"name": "[攻擊百分比-全部]隱世回光-5/5", "type": "攻擊百分比", "value": "0.15", "stack": "1", "duration": "30"}, {"name": "[普攻-下一位]散華-延奏技能-凜絜", "type": "加深", "value": "0.38", "stack": "1", "duration": "14"}, {"name": "[普攻]不滅航路-1諧振-普攻傷害時", "type": "加成", "value": "0.24", "stack": "1", "duration": "4"}, {"name": "[熱熔-自己]熔山裂谷-5/5", "type": "加成", "value": "0.3", "stack": "1", "duration": "15"}], "resonating_spin_concerto_regen": "", "accumulated_resonating_spin_concerto_regen": "", "time_start": "", "time_end": "", "cumulative_time": "", "frame": "", "comment": ""}, {"labels": [], "resonator_name": "布蘭特", "real_dmg_no_crit": "", "real_dmg_crit": "", "action": "", "skill_id": "空中攻擊第二段空翻傷害", "skill_bonus_type": "", "hit": "1", "buffs": [{"name": "[加成-下一位]無常凶鷺", "type": "加成", "value": "0.12", "stack": "1", "duration": "15"}, {"name": "[加成-全部]鳴鐘之龜", "type": "加成", "value": "0.1", "stack": "1", "duration": "15"}, {"name": "[加深-全部]維里奈-延奏技能-盛放", "type": "加深", "value": "0.15", "stack": "1", "duration": "30"}, {"name": "[攻擊-自己]布蘭特-共鳴回路-戲中人生", "type": "攻擊", "value": "1200", "stack": "1", "duration": ""}, {"name": "[攻擊百分比-全部]散華-共鳴鏈6-曙色天光", "type": "攻擊百分比", "value": "0.1", "stack": "2", "duration": "20"}, {"name": "[攻擊百分比-全部]維里奈-固有技能1-自然的獻禮", "type": "攻擊百分比", "value": "0.2", "stack": "1", "duration": "20"}, {"name": "[攻擊百分比-全部]隱世回光-5/5", "type": "攻擊百分比", "value": "0.15", "stack": "1", "duration": "30"}, {"name": "[普攻-下一位]散華-延奏技能-凜絜", "type": "加深", "value": "0.38", "stack": "1", "duration": "14"}, {"name": "[普攻]不滅航路-1諧振-普攻傷害時", "type": "加成", "value": "0.24", "stack": "1", "duration": "4"}, {"name": "[熱熔-自己]熔山裂谷-5/5", "type": "加成", "value": "0.3", "stack": "1", "duration": "15"}], "resonating_spin_concerto_regen": "", "accumulated_resonating_spin_concerto_regen": "", "time_start": "", "time_end": "00:15:28", "cumulative_time": "", "frame": "", "comment": ""}, {"labels": [], "resonator_name": "布蘭特", "real_dmg_no_crit": "", "real_dmg_crit": "", "action": "共鳴技能", "skill_id": "", "skill_bonus_type": "", "hit": "1", "buffs": [], "resonating_spin_concerto_regen": "", "accumulated_resonating_spin_concerto_regen": "", "time_start": "", "time_end": "", "cumulative_time": "", "frame": "", "comment": ""}, {"labels": [], "resonator_name": "布蘭特", "real_dmg_no_crit": "", "real_dmg_crit": "", "action": "共鳴技能", "skill_id": "火焰歸亡曲傷害", "skill_bonus_type": "", "hit": "1", "buffs": [{"name": "[加成-下一位]無常凶鷺", "type": "加成", "value": "0.12", "stack": "1", "duration": "15"}, {"name": "[加成-全部]鳴鐘之龜", "type": "加成", "value": "0.1", "stack": "1", "duration": "15"}, {"name": "[加深-全部]維里奈-延奏技能-盛放", "type": "加深", "value": "0.15", "stack": "1", "duration": "30"}, {"name": "[攻擊-自己]布蘭特-共鳴回路-戲中人生", "type": "攻擊", "value": "1200", "stack": "1", "duration": ""}, {"name": "[攻擊百分比-下一位]輕雲出月-5/5", "type": "攻擊百分比", "value": "0.225", "stack": "1", "duration": "15"}, {"name": "[攻擊百分比-全部]散華-共鳴鏈6-曙色天光", "type": "攻擊百分比", "value": "0.1", "stack": "2", "duration": "20"}, {"name": "[攻擊百分比-全部]維里奈-固有技能1-自然的獻禮", "type": "攻擊百分比", "value": "0.2", "stack": "1", "duration": "20"}, {"name": "[攻擊百分比-全部]隱世回光-5/5", "type": "攻擊百分比", "value": "0.15", "stack": "1", "duration": "30"}, {"name": "[普攻-下一位]散華-延奏技能-凜絜", "type": "加深", "value": "0.38", "stack": "1", "duration": "14"}, {"name": "[普攻]不滅航路-1諧振-普攻傷害時", "type": "加成", "value": "0.24", "stack": "1", "duration": "4"}, {"name": "[熱熔-自己]熔山裂谷-5/5", "type": "加成", "value": "0.3", "stack": "1", "duration": "15"}], "resonating_spin_concerto_regen": "", "accumulated_resonating_spin_concerto_regen": "", "time_start": "00:15:63", "time_end": "", "cumulative_time": "", "frame": "", "comment": ""}, {"labels": [], "resonator_name": "散華", "real_dmg_no_crit": "", "real_dmg_crit": "", "action": "", "skill_id": "冰棱爆炸傷害", "skill_bonus_type": "", "hit": "1", "buffs": [{"name": "[加成-下一位]無常凶鷺", "type": "加成", "value": "0.12", "stack": "1", "duration": "15"}, {"name": "[加成-全部]鳴鐘之龜", "type": "加成", "value": "0.1", "stack": "1", "duration": "15"}, {"name": "[加深-全部]維里奈-延奏技能-盛放", "type": "加深", "value": "0.15", "stack": "1", "duration": "30"}, {"name": "[攻擊百分比-全部]散華-共鳴鏈6-曙色天光", "type": "攻擊百分比", "value": "0.1", "stack": "2", "duration": "20"}, {"name": "[攻擊百分比-全部]維里奈-固有技能1-自然的獻禮", "type": "攻擊百分比", "value": "0.2", "stack": "1", "duration": "20"}, {"name": "[攻擊百分比-全部]隱世回光-5/5", "type": "攻擊百分比", "value": "0.15", "stack": "1", "duration": "30"}, {"name": "[暴擊傷害-自己]散華-共鳴鏈5-顛覆無常", "type": "暴擊傷害", "value": "1.0", "stack": "1", "duration": ""}], "resonating_spin_concerto_regen": "", "accumulated_resonating_spin_concerto_regen": "", "time_start": "", "time_end": "", "cumulative_time": "", "frame": "", "comment": ""}, {"labels": [], "resonator_name": "布蘭特", "real_dmg_no_crit": "", "real_dmg_crit": "", "action": "共鳴解放", "skill_id": "直到世界盡頭", "skill_bonus_type": "", "hit": "1", "buffs": [{"name": "[加成-下一位]無常凶鷺", "type": "加成", "value": "0.12", "stack": "1", "duration": "15"}, {"name": "[加成-全部]鳴鐘之龜", "type": "加成", "value": "0.1", "stack": "1", "duration": "15"}, {"name": "[加深-全部]維里奈-延奏技能-盛放", "type": "加深", "value": "0.15", "stack": "1", "duration": "30"}, {"name": "[攻擊-自己]布蘭特-共鳴回路-戲中人生", "type": "攻擊", "value": "1200", "stack": "1", "duration": ""}, {"name": "[攻擊百分比-下一位]輕雲出月-5/5", "type": "攻擊百分比", "value": "0.225", "stack": "1", "duration": "15"}, {"name": "[攻擊百分比-全部]散華-共鳴鏈6-曙色天光", "type": "攻擊百分比", "value": "0.1", "stack": "2", "duration": "20"}, {"name": "[攻擊百分比-全部]維里奈-固有技能1-自然的獻禮", "type": "攻擊百分比", "value": "0.2", "stack": "1", "duration": "20"}, {"name": "[攻擊百分比-全部]隱世回光-5/5", "type": "攻擊百分比", "value": "0.15", "stack": "1", "duration": "30"}, {"name": "[熱熔-自己]熔山裂谷-5/5", "type": "加成", "value": "0.3", "stack": "1", "duration": "15"}], "resonating_spin_concerto_regen": "", "accumulated_resonating_spin_concerto_regen": "", "time_start": "00:17:90", "time_end": "00:17:92", "cumulative_time": "", "frame": "", "comment": "共鳴解放完普攻時機要抓一下，沒按好人會在地上。"}, {"labels": [], "resonator_name": "布蘭特", "real_dmg_no_crit": "", "real_dmg_crit": "", "action": "空中攻擊", "skill_id": "空中攻擊第一段傷害", "skill_bonus_type": "", "hit": "1", "buffs": [{"name": "[加成-下一位]無常凶鷺", "type": "加成", "value": "0.12", "stack": "1", "duration": "15"}, {"name": "[加成-全部]鳴鐘之龜", "type": "加成", "value": "0.1", "stack": "1", "duration": "15"}, {"name": "[加深-全部]維里奈-延奏技能-盛放", "type": "加深", "value": "0.15", "stack": "1", "duration": "30"}, {"name": "[攻擊-自己]布蘭特-共鳴回路-「我」的人生", "type": "攻擊", "value": "2000", "stack": "1", "duration": "12"}, {"name": "[攻擊百分比-下一位]輕雲出月-5/5", "type": "攻擊百分比", "value": "0.225", "stack": "1", "duration": "15"}, {"name": "[攻擊百分比-全部]散華-共鳴鏈6-曙色天光", "type": "攻擊百分比", "value": "0.1", "stack": "2", "duration": "20"}, {"name": "[攻擊百分比-全部]維里奈-固有技能1-自然的獻禮", "type": "攻擊百分比", "value": "0.2", "stack": "1", "duration": "20"}, {"name": "[攻擊百分比-全部]隱世回光-5/5", "type": "攻擊百分比", "value": "0.15", "stack": "1", "duration": "30"}, {"name": "[普攻-下一位]散華-延奏技能-凜絜", "type": "加深", "value": "0.38", "stack": "1", "duration": "14"}, {"name": "[普攻]不滅航路-1諧振-共鳴解放後", "type": "加成", "value": "0.24", "stack": "1", "duration": "10"}, {"name": "[普攻]不滅航路-1諧振-普攻傷害時", "type": "加成", "value": "0.24", "stack": "1", "duration": "4"}, {"name": "[熱熔-自己]熔山裂谷-5/5", "type": "加成", "value": "0.3", "stack": "1", "duration": "15"}], "resonating_spin_concerto_regen": "", "accumulated_resonating_spin_concerto_regen": "", "time_start": "", "time_end": "", "cumulative_time": "", "frame": "", "comment": ""}, {"labels": [], "resonator_name": "布蘭特", "real_dmg_no_crit": "", "real_dmg_crit": "", "action": "", "skill_id": "空中攻擊第一段空翻傷害", "skill_bonus_type": "", "hit": "1", "buffs": [{"name": "[加成-下一位]無常凶鷺", "type": "加成", "value": "0.12", "stack": "1", "duration": "15"}, {"name": "[加深-全部]維里奈-延奏技能-盛放", "type": "加深", "value": "0.15", "stack": "1", "duration": "30"}, {"name": "[攻擊-自己]布蘭特-共鳴回路-「我」的人生", "type": "攻擊", "value": "2000", "stack": "1", "duration": "12"}, {"name": "[攻擊百分比-下一位]輕雲出月-5/5", "type": "攻擊百分比", "value": "0.225", "stack": "1", "duration": "15"}, {"name": "[攻擊百分比-全部]散華-共鳴鏈6-曙色天光", "type": "攻擊百分比", "value": "0.1", "stack": "2", "duration": "20"}, {"name": "[攻擊百分比-全部]維里奈-固有技能1-自然的獻禮", "type": "攻擊百分比", "value": "0.2", "stack": "1", "duration": "20"}, {"name": "[攻擊百分比-全部]隱世回光-5/5", "type": "攻擊百分比", "value": "0.15", "stack": "1", "duration": "30"}, {"name": "[普攻-下一位]散華-延奏技能-凜絜", "type": "加深", "value": "0.38", "stack": "1", "duration": "14"}, {"name": "[普攻]不滅航路-1諧振-共鳴解放後", "type": "加成", "value": "0.24", "stack": "1", "duration": "10"}, {"name": "[普攻]不滅航路-1諧振-普攻傷害時", "type": "加成", "value": "0.24", "stack": "1", "duration": "4"}, {"name": "[熱熔-自己]熔山裂谷-5/5", "type": "加成", "value": "0.3", "stack": "1", "duration": "15"}], "resonating_spin_concerto_regen": "", "accumulated_resonating_spin_concerto_regen": "", "time_start": "", "time_end": "", "cumulative_time": "", "frame": "", "comment": ""}, {"labels": [], "resonator_name": "布蘭特", "real_dmg_no_crit": "", "real_dmg_crit": "", "action": "空中攻擊", "skill_id": "空中攻擊第二段傷害", "skill_bonus_type": "", "hit": "1", "buffs": [{"name": "[加成-下一位]無常凶鷺", "type": "加成", "value": "0.12", "stack": "1", "duration": "15"}, {"name": "[加深-全部]維里奈-延奏技能-盛放", "type": "加深", "value": "0.15", "stack": "1", "duration": "30"}, {"name": "[攻擊-自己]布蘭特-共鳴回路-「我」的人生", "type": "攻擊", "value": "2000", "stack": "1", "duration": "12"}, {"name": "[攻擊百分比-下一位]輕雲出月-5/5", "type": "攻擊百分比", "value": "0.225", "stack": "1", "duration": "15"}, {"name": "[攻擊百分比-全部]散華-共鳴鏈6-曙色天光", "type": "攻擊百分比", "value": "0.1", "stack": "2", "duration": "20"}, {"name": "[攻擊百分比-全部]維里奈-固有技能1-自然的獻禮", "type": "攻擊百分比", "value": "0.2", "stack": "1", "duration": "20"}, {"name": "[攻擊百分比-全部]隱世回光-5/5", "type": "攻擊百分比", "value": "0.15", "stack": "1", "duration": "30"}, {"name": "[普攻-下一位]散華-延奏技能-凜絜", "type": "加深", "value": "0.38", "stack": "1", "duration": "14"}, {"name": "[普攻]不滅航路-1諧振-共鳴解放後", "type": "加成", "value": "0.24", "stack": "1", "duration": "10"}, {"name": "[普攻]不滅航路-1諧振-普攻傷害時", "type": "加成", "value": "0.24", "stack": "1", "duration": "4"}, {"name": "[熱熔-自己]熔山裂谷-5/5", "type": "加成", "value": "0.3", "stack": "1", "duration": "15"}], "resonating_spin_concerto_regen": "", "accumulated_resonating_spin_concerto_regen": "", "time_start": "", "time_end": "", "cumulative_time": "", "frame": "", "comment": ""}, {"labels": [], "resonator_name": "布蘭特", "real_dmg_no_crit": "", "real_dmg_crit": "", "action": "", "skill_id": "空中攻擊第二段空翻傷害", "skill_bonus_type": "", "hit": "1", "buffs": [{"name": "[加成-下一位]無常凶鷺", "type": "加成", "value": "0.12", "stack": "1", "duration": "15"}, {"name": "[加深-全部]維里奈-延奏技能-盛放", "type": "加深", "value": "0.15", "stack": "1", "duration": "30"}, {"name": "[攻擊-自己]布蘭特-共鳴回路-「我」的人生", "type": "攻擊", "value": "2000", "stack": "1", "duration": "12"}, {"name": "[攻擊百分比-下一位]輕雲出月-5/5", "type": "攻擊百分比", "value": "0.225", "stack": "1", "duration": "15"}, {"name": "[攻擊百分比-全部]散華-共鳴鏈6-曙色天光", "type": "攻擊百分比", "value": "0.1", "stack": "2", "duration": "20"}, {"name": "[攻擊百分比-全部]維里奈-固有技能1-自然的獻禮", "type": "攻擊百分比", "value": "0.2", "stack": "1", "duration": "20"}, {"name": "[攻擊百分比-全部]隱世回光-5/5", "type": "攻擊百分比", "value": "0.15", "stack": "1", "duration": "30"}, {"name": "[普攻-下一位]散華-延奏技能-凜絜", "type": "加深", "value": "0.38", "stack": "1", "duration": "14"}, {"name": "[普攻]不滅航路-1諧振-共鳴解放後", "type": "加成", "value": "0.24", "stack": "1", "duration": "10"}, {"name": "[普攻]不滅航路-1諧振-普攻傷害時", "type": "加成", "value": "0.24", "stack": "1", "duration": "4"}, {"name": "[熱熔-自己]熔山裂谷-5/5", "type": "加成", "value": "0.3", "stack": "1", "duration": "15"}], "resonating_spin_concerto_regen": "", "accumulated_resonating_spin_concerto_regen": "", "time_start": "", "time_end": "", "cumulative_time": "", "frame": "", "comment": ""}, {"labels": [], "resonator_name": "布蘭特", "real_dmg_no_crit": "", "real_dmg_crit": "", "action": "空中攻擊", "skill_id": "空中攻擊第三段傷害", "skill_bonus_type": "", "hit": "1", "buffs": [{"name": "[加成-下一位]無常凶鷺", "type": "加成", "value": "0.12", "stack": "1", "duration": "15"}, {"name": "[加深-全部]維里奈-延奏技能-盛放", "type": "加深", "value": "0.15", "stack": "1", "duration": "30"}, {"name": "[攻擊-自己]布蘭特-共鳴回路-「我」的人生", "type": "攻擊", "value": "2000", "stack": "1", "duration": "12"}, {"name": "[攻擊百分比-下一位]輕雲出月-5/5", "type": "攻擊百分比", "value": "0.225", "stack": "1", "duration": "15"}, {"name": "[攻擊百分比-全部]散華-共鳴鏈6-曙色天光", "type": "攻擊百分比", "value": "0.1", "stack": "1", "duration": "20"}, {"name": "[攻擊百分比-全部]維里奈-固有技能1-自然的獻禮", "type": "攻擊百分比", "value": "0.2", "stack": "1", "duration": "20"}, {"name": "[攻擊百分比-全部]隱世回光-5/5", "type": "攻擊百分比", "value": "0.15", "stack": "1", "duration": "30"}, {"name": "[普攻-下一位]散華-延奏技能-凜絜", "type": "加深", "value": "0.38", "stack": "1", "duration": "14"}, {"name": "[普攻]不滅航路-1諧振-共鳴解放後", "type": "加成", "value": "0.24", "stack": "1", "duration": "10"}, {"name": "[普攻]不滅航路-1諧振-普攻傷害時", "type": "加成", "value": "0.24", "stack": "1", "duration": "4"}, {"name": "[熱熔-自己]熔山裂谷-5/5", "type": "加成", "value": "0.3", "stack": "1", "duration": "15"}], "resonating_spin_concerto_regen": "", "accumulated_resonating_spin_concerto_regen": "", "time_start": "", "time_end": "", "cumulative_time": "", "frame": "", "comment": ""}, {"labels": [], "resonator_name": "布蘭特", "real_dmg_no_crit": "", "real_dmg_crit": "", "action": "", "skill_id": "空中攻擊第三段空翻傷害", "skill_bonus_type": "", "hit": "1", "buffs": [{"name": "[加成-下一位]無常凶鷺", "type": "加成", "value": "0.12", "stack": "1", "duration": "15"}, {"name": "[加深-全部]維里奈-延奏技能-盛放", "type": "加深", "value": "0.15", "stack": "1", "duration": "30"}, {"name": "[攻擊-自己]布蘭特-共鳴回路-「我」的人生", "type": "攻擊", "value": "2000", "stack": "1", "duration": "12"}, {"name": "[攻擊百分比-下一位]輕雲出月-5/5", "type": "攻擊百分比", "value": "0.225", "stack": "1", "duration": "15"}, {"name": "[攻擊百分比-全部]散華-共鳴鏈6-曙色天光", "type": "攻擊百分比", "value": "0.1", "stack": "1", "duration": "20"}, {"name": "[攻擊百分比-全部]維里奈-固有技能1-自然的獻禮", "type": "攻擊百分比", "value": "0.2", "stack": "1", "duration": "20"}, {"name": "[攻擊百分比-全部]隱世回光-5/5", "type": "攻擊百分比", "value": "0.15", "stack": "1", "duration": "30"}, {"name": "[普攻-下一位]散華-延奏技能-凜絜", "type": "加深", "value": "0.38", "stack": "1", "duration": "14"}, {"name": "[普攻]不滅航路-1諧振-共鳴解放後", "type": "加成", "value": "0.24", "stack": "1", "duration": "10"}, {"name": "[普攻]不滅航路-1諧振-普攻傷害時", "type": "加成", "value": "0.24", "stack": "1", "duration": "4"}, {"name": "[熱熔-自己]熔山裂谷-5/5", "type": "加成", "value": "0.3", "stack": "1", "duration": "15"}], "resonating_spin_concerto_regen": "", "accumulated_resonating_spin_concerto_regen": "", "time_start": "", "time_end": "", "cumulative_time": "", "frame": "", "comment": ""}, {"labels": [], "resonator_name": "布蘭特", "real_dmg_no_crit": "", "real_dmg_crit": "", "action": "空中攻擊", "skill_id": "空中攻擊第四段傷害", "skill_bonus_type": "", "hit": "1", "buffs": [{"name": "[加成-下一位]無常凶鷺", "type": "加成", "value": "0.12", "stack": "1", "duration": "15"}, {"name": "[加深-全部]維里奈-延奏技能-盛放", "type": "加深", "value": "0.15", "stack": "1", "duration": "30"}, {"name": "[攻擊-自己]布蘭特-共鳴回路-「我」的人生", "type": "攻擊", "value": "2000", "stack": "1", "duration": "12"}, {"name": "[攻擊百分比-下一位]輕雲出月-5/5", "type": "攻擊百分比", "value": "0.225", "stack": "1", "duration": "15"}, {"name": "[攻擊百分比-全部]散華-共鳴鏈6-曙色天光", "type": "攻擊百分比", "value": "0.1", "stack": "1", "duration": "20"}, {"name": "[攻擊百分比-全部]維里奈-固有技能1-自然的獻禮", "type": "攻擊百分比", "value": "0.2", "stack": "1", "duration": "20"}, {"name": "[攻擊百分比-全部]隱世回光-5/5", "type": "攻擊百分比", "value": "0.15", "stack": "1", "duration": "30"}, {"name": "[普攻-下一位]散華-延奏技能-凜絜", "type": "加深", "value": "0.38", "stack": "1", "duration": "14"}, {"name": "[普攻]不滅航路-1諧振-共鳴解放後", "type": "加成", "value": "0.24", "stack": "1", "duration": "10"}, {"name": "[普攻]不滅航路-1諧振-普攻傷害時", "type": "加成", "value": "0.24", "stack": "1", "duration": "4"}, {"name": "[熱熔-自己]熔山裂谷-5/5", "type": "加成", "value": "0.3", "stack": "1", "duration": "15"}], "resonating_spin_concerto_regen": "", "accumulated_resonating_spin_concerto_regen": "", "time_start": "", "time_end": "", "cumulative_time": "", "frame": "", "comment": ""}, {"labels": [], "resonator_name": "布蘭特", "real_dmg_no_crit": "", "real_dmg_crit": "", "action": "共鳴技能", "skill_id": "", "skill_bonus_type": "", "hit": "1", "buffs": [], "resonating_spin_concerto_regen": "", "accumulated_resonating_spin_concerto_regen": "", "time_start": "", "time_end": "", "cumulative_time": "", "frame": "", "comment": ""}, {"labels": [], "resonator_name": "布蘭特", "real_dmg_no_crit": "", "real_dmg_crit": "", "action": "共鳴技能", "skill_id": "火焰歸亡曲傷害", "skill_bonus_type": "", "hit": "1", "buffs": [{"name": "[加成-下一位]無常凶鷺", "type": "加成", "value": "0.12", "stack": "1", "duration": "15"}, {"name": "[加深-全部]維里奈-延奏技能-盛放", "type": "加深", "value": "0.15", "stack": "1", "duration": "30"}, {"name": "[攻擊-自己]布蘭特-共鳴回路-「我」的人生", "type": "攻擊", "value": "2000", "stack": "1", "duration": "12"}, {"name": "[攻擊百分比-下一位]輕雲出月-5/5", "type": "攻擊百分比", "value": "0.225", "stack": "1", "duration": "15"}, {"name": "[攻擊百分比-全部]散華-共鳴鏈6-曙色天光", "type": "攻擊百分比", "value": "0.1", "stack": "1", "duration": "20"}, {"name": "[攻擊百分比-全部]維里奈-固有技能1-自然的獻禮", "type": "攻擊百分比", "value": "0.2", "stack": "1", "duration": "20"}, {"name": "[攻擊百分比-全部]隱世回光-5/5", "type": "攻擊百分比", "value": "0.15", "stack": "1", "duration": "30"}, {"name": "[普攻-下一位]散華-延奏技能-凜絜", "type": "加深", "value": "0.38", "stack": "1", "duration": "14"}, {"name": "[普攻]不滅航路-1諧振-共鳴解放後", "type": "加成", "value": "0.24", "stack": "1", "duration": "10"}, {"name": "[普攻]不滅航路-1諧振-普攻傷害時", "type": "加成", "value": "0.24", "stack": "1", "duration": "4"}, {"name": "[熱熔-自己]熔山裂谷-5/5", "type": "加成", "value": "0.3", "stack": "1", "duration": "15"}], "resonating_spin_concerto_regen": "", "accumulated_resonating_spin_concerto_regen": "", "time_start": "00:24:12", "time_end": "", "cumulative_time": "", "frame": "", "comment": ""}, {"labels": [], "resonator_name": "布蘭特", "real_dmg_no_crit": "", "real_dmg_crit": "", "action": "變奏", "skill_id": "", "skill_bonus_type": "", "hit": "1", "buffs": [], "resonating_spin_concerto_regen": "", "accumulated_resonating_spin_concerto_regen": "", "time_start": "00:24:64", "time_end": "", "cumulative_time": "", "frame": "", "comment": "直接循環。"}]}, "resonator_ids": ["[20有效-小Ｏ] +0布蘭特+1不滅航路 4暴3共效3共效1攻1攻", "[20有效-小Ｏ] +0布蘭特+1不滅航路 4暴3共效3攻1攻1攻", "[20有效-小Ｏ] +0布蘭特+1不滅航路 4暴3共效3熱熔1攻1攻", "[20有效-小Ｏ] +0布蘭特+1不滅航路 4暴傷3共效3共效1攻1攻", "[20有效-小Ｏ] +0布蘭特+1不滅航路 4暴傷3共效3攻1攻1攻", "[20有效-小Ｏ] +0布蘭特+1不滅航路 4暴傷3共效3熱熔1攻1攻", "[20有效-小Ｏ] +0布蘭特+1不滅航路 4攻3共效3共效1攻1攻", "[20有效-小Ｏ] +0布蘭特+1不滅航路 4攻3共效3攻1攻1攻", "[20有效-小Ｏ] +0布蘭特+1不滅航路 4攻3共效3熱熔1攻1攻"], "resonator_models": {"[20有效-小Ｏ] +0布蘭特+1不滅航路 4暴3共效3共效1攻1攻": {"resonator_src": "/assets/resonator/icon/布蘭特.png", "element": "熱熔", "element_src": "/assets/element/icon/熱熔.png", "element_en": "fusion", "name": "布蘭特", "chain": "0", "weapon_name": "不滅航路", "weapon_rank": "1", "weapon_level": "90", "level": "90", "hp": "16,235.00", "attack": "2,068.91", "defense": "1,307.00", "crit_rate": "85.00%", "crit_dmg": "234.00%", "energy_regen": "241.00%", "resonance_skill_dmg_bonus": "12.00%", "basic_attack_dmg_bonus": "0.00%", "heavy_attack_dmg_bonus": "0.00%", "resonance_liberation_dmg_bonus": "0.00%", "healing_bonus": "0.00%", "physical_dmg_bonus": "0.00%", "glacio_dmg_bonus": "0.00%", "fusion_dmg_bonus": "37.00%", "electro_dmg_bonus": "0.00%", "aero_dmg_bonus": "0.00%", "spectro_dmg_bonus": "0.00%", "havoc_dmg_bonus": "0.00%", "physical_dmg_res": "0.00%", "glacio_dmg_res": "0.00%", "fusion_dmg_res": "0.00%", "electro_dmg_res": "0.00%", "aero_dmg_res": "0.00%", "spectro_dmg_res": "0.00%", "havoc_dmg_res": "0.00%", "normal_attack_lv": "10", "resonance_skill_lv": "10", "resonance_liberation_lv": "10", "forte_circuit_lv": "10", "intro_skill_lv": "10", "inherent_skill_1": "1", "inherent_skill_2": "1", "echo_hp": "4,560.00", "echo_hp_p": "0.00%", "echo_atk": "550.00", "echo_atk_p": "81.00%", "echo_def": "", "echo_def_p": "0.00%", "echo_crit_rate": "64.00%", "echo_crit_dmg": "84.00%", "echo_energy_regen": "64.00%", "echo_sonata_1": "熔山裂谷", "echo_sonata_2": "熔山裂谷", "echo_sonata_3": "熔山裂谷", "echo_sonata_4": "熔山裂谷", "echo_sonata_5": "熔山裂谷", "echo_resonance_skill_dmg_bonus": "12.00%", "echo_basic_attack_dmg_bonus": "0.00%", "echo_heavy_attack_dmg_bonus": "0.00%", "echo_resonance_liberation_dmg_bonus": "0.00%", "echo_healing_bonus": "0.00%", "echo_glacio_dmg_bonus": "0.00%", "echo_fusion_dmg_bonus": "22.00%", "echo_electro_dmg_bonus": "0.00%", "echo_aero_dmg_bonus": "0.00%", "echo_spectro_dmg_bonus": "0.00%", "echo_havoc_dmg_bonus": "0.00%"}, "[20有效-小Ｏ] +0布蘭特+1不滅航路 4暴3共效3攻1攻1攻": {"resonator_src": "/assets/resonator/icon/布蘭特.png", "element": "熱熔", "element_src": "/assets/element/icon/熱熔.png", "element_en": "fusion", "name": "布蘭特", "chain": "0", "weapon_name": "不滅航路", "weapon_rank": "1", "weapon_level": "90", "level": "90", "hp": "16,235.00", "attack": "2,305.01", "defense": "1,307.00", "crit_rate": "85.00%", "crit_dmg": "234.00%", "energy_regen": "209.00%", "resonance_skill_dmg_bonus": "12.00%", "basic_attack_dmg_bonus": "0.00%", "heavy_attack_dmg_bonus": "0.00%", "resonance_liberation_dmg_bonus": "0.00%", "healing_bonus": "0.00%", "physical_dmg_bonus": "0.00%", "glacio_dmg_bonus": "0.00%", "fusion_dmg_bonus": "37.00%", "electro_dmg_bonus": "0.00%", "aero_dmg_bonus": "0.00%", "spectro_dmg_bonus": "0.00%", "havoc_dmg_bonus": "0.00%", "physical_dmg_res": "0.00%", "glacio_dmg_res": "0.00%", "fusion_dmg_res": "0.00%", "electro_dmg_res": "0.00%", "aero_dmg_res": "0.00%", "spectro_dmg_res": "0.00%", "havoc_dmg_res": "0.00%", "normal_attack_lv": "10", "resonance_skill_lv": "10", "resonance_liberation_lv": "10", "forte_circuit_lv": "10", "intro_skill_lv": "10", "inherent_skill_1": "1", "inherent_skill_2": "1", "echo_hp": "4,560.00", "echo_hp_p": "0.00%", "echo_atk": "550.00", "echo_atk_p": "111.00%", "echo_def": "", "echo_def_p": "0.00%", "echo_crit_rate": "64.00%", "echo_crit_dmg": "84.00%", "echo_energy_regen": "32.00%", "echo_sonata_1": "熔山裂谷", "echo_sonata_2": "熔山裂谷", "echo_sonata_3": "熔山裂谷", "echo_sonata_4": "熔山裂谷", "echo_sonata_5": "熔山裂谷", "echo_resonance_skill_dmg_bonus": "12.00%", "echo_basic_attack_dmg_bonus": "0.00%", "echo_heavy_attack_dmg_bonus": "0.00%", "echo_resonance_liberation_dmg_bonus": "0.00%", "echo_healing_bonus": "0.00%", "echo_glacio_dmg_bonus": "0.00%", "echo_fusion_dmg_bonus": "22.00%", "echo_electro_dmg_bonus": "0.00%", "echo_aero_dmg_bonus": "0.00%", "echo_spectro_dmg_bonus": "0.00%", "echo_havoc_dmg_bonus": "0.00%"}, "[20有效-小Ｏ] +0布蘭特+1不滅航路 4暴3共效3熱熔1攻1攻": {"resonator_src": "/assets/resonator/icon/布蘭特.png", "element": "熱熔", "element_src": "/assets/element/icon/熱熔.png", "element_en": "fusion", "name": "布蘭特", "chain": "0", "weapon_name": "不滅航路", "weapon_rank": "1", "weapon_level": "90", "level": "90", "hp": "16,235.00", "attack": "2,068.91", "defense": "1,307.00", "crit_rate": "85.00%", "crit_dmg": "234.00%", "energy_regen": "209.00%", "resonance_skill_dmg_bonus": "12.00%", "basic_attack_dmg_bonus": "0.00%", "heavy_attack_dmg_bonus": "0.00%", "resonance_liberation_dmg_bonus": "0.00%", "healing_bonus": "0.00%", "physical_dmg_bonus": "0.00%", "glacio_dmg_bonus": "0.00%", "fusion_dmg_bonus": "67.00%", "electro_dmg_bonus": "0.00%", "aero_dmg_bonus": "0.00%", "spectro_dmg_bonus": "0.00%", "havoc_dmg_bonus": "0.00%", "physical_dmg_res": "0.00%", "glacio_dmg_res": "0.00%", "fusion_dmg_res": "0.00%", "electro_dmg_res": "0.00%", "aero_dmg_res": "0.00%", "spectro_dmg_res": "0.00%", "havoc_dmg_res": "0.00%", "normal_attack_lv": "10", "resonance_skill_lv": "10", "resonance_liberation_lv": "10", "forte_circuit_lv": "10", "intro_skill_lv": "10", "inherent_skill_1": "1", "inherent_skill_2": "1", "echo_hp": "4,560.00", "echo_hp_p": "0.00%", "echo_atk": "550.00", "echo_atk_p": "81.00%", "echo_def": "", "echo_def_p": "0.00%", "echo_crit_rate": "64.00%", "echo_crit_dmg": "84.00%", "echo_energy_regen": "32.00%", "echo_sonata_1": "熔山裂谷", "echo_sonata_2": "熔山裂谷", "echo_sonata_3": "熔山裂谷", "echo_sonata_4": "熔山裂谷", "echo_sonata_5": "熔山裂谷", "echo_resonance_skill_dmg_bonus": "12.00%", "echo_basic_attack_dmg_bonus": "0.00%", "echo_heavy_attack_dmg_bonus": "0.00%", "echo_resonance_liberation_dmg_bonus": "0.00%", "echo_healing_bonus": "0.00%", "echo_glacio_dmg_bonus": "0.00%", "echo_fusion_dmg_bonus": "52.00%", "echo_electro_dmg_bonus": "0.00%", "echo_aero_dmg_bonus": "0.00%", "echo_spectro_dmg_bonus": "0.00%", "echo_havoc_dmg_bonus": "0.00%"}, "[20有效-小Ｏ] +0布蘭特+1不滅航路 4暴傷3共效3共效1攻1攻": {"resonator_src": "/assets/resonator/icon/布蘭特.png", "element": "熱熔", "element_src": "/assets/element/icon/熱熔.png", "element_en": "fusion", "name": "布蘭特", "chain": "0", "weapon_name": "不滅航路", "weapon_rank": "1", "weapon_level": "90", "level": "90", "hp": "16,235.00", "attack": "2,068.91", "defense": "1,307.00", "crit_rate": "63.00%", "crit_dmg": "278.00%", "energy_regen": "241.00%", "resonance_skill_dmg_bonus": "12.00%", "basic_attack_dmg_bonus": "0.00%", "heavy_attack_dmg_bonus": "0.00%", "resonance_liberation_dmg_bonus": "0.00%", "healing_bonus": "0.00%", "physical_dmg_bonus": "0.00%", "glacio_dmg_bonus": "0.00%", "fusion_dmg_bonus": "37.00%", "electro_dmg_bonus": "0.00%", "aero_dmg_bonus": "0.00%", "spectro_dmg_bonus": "0.00%", "havoc_dmg_bonus": "0.00%", "physical_dmg_res": "0.00%", "glacio_dmg_res": "0.00%", "fusion_dmg_res": "0.00%", "electro_dmg_res": "0.00%", "aero_dmg_res": "0.00%", "spectro_dmg_res": "0.00%", "havoc_dmg_res": "0.00%", "normal_attack_lv": "10", "resonance_skill_lv": "10", "resonance_liberation_lv": "10", "forte_circuit_lv": "10", "intro_skill_lv": "10", "inherent_skill_1": "1", "inherent_skill_2": "1", "echo_hp": "4,560.00", "echo_hp_p": "0.00%", "echo_atk": "550.00", "echo_atk_p": "81.00%", "echo_def": "", "echo_def_p": "0.00%", "echo_crit_rate": "42.00%", "echo_crit_dmg": "128.00%", "echo_energy_regen": "64.00%", "echo_sonata_1": "熔山裂谷", "echo_sonata_2": "熔山裂谷", "echo_sonata_3": "熔山裂谷", "echo_sonata_4": "熔山裂谷", "echo_sonata_5": "熔山裂谷", "echo_resonance_skill_dmg_bonus": "12.00%", "echo_basic_attack_dmg_bonus": "0.00%", "echo_heavy_attack_dmg_bonus": "0.00%", "echo_resonance_liberation_dmg_bonus": "0.00%", "echo_healing_bonus": "0.00%", "echo_glacio_dmg_bonus": "0.00%", "echo_fusion_dmg_bonus": "22.00%", "echo_electro_dmg_bonus": "0.00%", "echo_aero_dmg_bonus": "0.00%", "echo_spectro_dmg_bonus": "0.00%", "echo_havoc_dmg_bonus": "0.00%"}, "[20有效-小Ｏ] +0布蘭特+1不滅航路 4暴傷3共效3攻1攻1攻": {"resonator_src": "/assets/resonator/icon/布蘭特.png", "element": "熱熔", "element_src": "/assets/element/icon/熱熔.png", "element_en": "fusion", "name": "布蘭特", "chain": "0", "weapon_name": "不滅航路", "weapon_rank": "1", "weapon_level": "90", "level": "90", "hp": "16,235.00", "attack": "2,305.01", "defense": "1,307.00", "crit_rate": "63.00%", "crit_dmg": "278.00%", "energy_regen": "209.00%", "resonance_skill_dmg_bonus": "12.00%", "basic_attack_dmg_bonus": "0.00%", "heavy_attack_dmg_bonus": "0.00%", "resonance_liberation_dmg_bonus": "0.00%", "healing_bonus": "0.00%", "physical_dmg_bonus": "0.00%", "glacio_dmg_bonus": "0.00%", "fusion_dmg_bonus": "37.00%", "electro_dmg_bonus": "0.00%", "aero_dmg_bonus": "0.00%", "spectro_dmg_bonus": "0.00%", "havoc_dmg_bonus": "0.00%", "physical_dmg_res": "0.00%", "glacio_dmg_res": "0.00%", "fusion_dmg_res": "0.00%", "electro_dmg_res": "0.00%", "aero_dmg_res": "0.00%", "spectro_dmg_res": "0.00%", "havoc_dmg_res": "0.00%", "normal_attack_lv": "10", "resonance_skill_lv": "10", "resonance_liberation_lv": "10", "forte_circuit_lv": "10", "intro_skill_lv": "10", "inherent_skill_1": "1", "inherent_skill_2": "1", "echo_hp": "4,560.00", "echo_hp_p": "0.00%", "echo_atk": "550.00", "echo_atk_p": "111.00%", "echo_def": "", "echo_def_p": "0.00%", "echo_crit_rate": "42.00%", "echo_crit_dmg": "128.00%", "echo_energy_regen": "32.00%", "echo_sonata_1": "熔山裂谷", "echo_sonata_2": "熔山裂谷", "echo_sonata_3": "熔山裂谷", "echo_sonata_4": "熔山裂谷", "echo_sonata_5": "熔山裂谷", "echo_resonance_skill_dmg_bonus": "12.00%", "echo_basic_attack_dmg_bonus": "0.00%", "echo_heavy_attack_dmg_bonus": "0.00%", "echo_resonance_liberation_dmg_bonus": "0.00%", "echo_healing_bonus": "0.00%", "echo_glacio_dmg_bonus": "0.00%", "echo_fusion_dmg_bonus": "22.00%", "echo_electro_dmg_bonus": "0.00%", "echo_aero_dmg_bonus": "0.00%", "echo_spectro_dmg_bonus": "0.00%", "echo_havoc_dmg_bonus": "0.00%"}, "[20有效-小Ｏ] +0布蘭特+1不滅航路 4暴傷3共效3熱熔1攻1攻": {"resonator_src": "/assets/resonator/icon/布蘭特.png", "element": "熱熔", "element_src": "/assets/element/icon/熱熔.png", "element_en": "fusion", "name": "布蘭特", "chain": "0", "weapon_name": "不滅航路", "weapon_rank": "1", "weapon_level": "90", "level": "90", "hp": "16,235.00", "attack": "2,068.91", "defense": "1,307.00", "crit_rate": "63.00%", "crit_dmg": "278.00%", "energy_regen": "209.00%", "resonance_skill_dmg_bonus": "12.00%", "basic_attack_dmg_bonus": "0.00%", "heavy_attack_dmg_bonus": "0.00%", "resonance_liberation_dmg_bonus": "0.00%", "healing_bonus": "0.00%", "physical_dmg_bonus": "0.00%", "glacio_dmg_bonus": "0.00%", "fusion_dmg_bonus": "67.00%", "electro_dmg_bonus": "0.00%", "aero_dmg_bonus": "0.00%", "spectro_dmg_bonus": "0.00%", "havoc_dmg_bonus": "0.00%", "physical_dmg_res": "0.00%", "glacio_dmg_res": "0.00%", "fusion_dmg_res": "0.00%", "electro_dmg_res": "0.00%", "aero_dmg_res": "0.00%", "spectro_dmg_res": "0.00%", "havoc_dmg_res": "0.00%", "normal_attack_lv": "10", "resonance_skill_lv": "10", "resonance_liberation_lv": "10", "forte_circuit_lv": "10", "intro_skill_lv": "10", "inherent_skill_1": "1", "inherent_skill_2": "1", "echo_hp": "4,560.00", "echo_hp_p": "0.00%", "echo_atk": "550.00", "echo_atk_p": "81.00%", "echo_def": "", "echo_def_p": "0.00%", "echo_crit_rate": "42.00%", "echo_crit_dmg": "128.00%", "echo_energy_regen": "32.00%", "echo_sonata_1": "熔山裂谷", "echo_sonata_2": "熔山裂谷", "echo_sonata_3": "熔山裂谷", "echo_sonata_4": "熔山裂谷", "echo_sonata_5": "熔山裂谷", "echo_resonance_skill_dmg_bonus": "12.00%", "echo_basic_attack_dmg_bonus": "0.00%", "echo_heavy_attack_dmg_bonus": "0.00%", "echo_resonance_liberation_dmg_bonus": "0.00%", "echo_healing_bonus": "0.00%", "echo_glacio_dmg_bonus": "0.00%", "echo_fusion_dmg_bonus": "52.00%", "echo_electro_dmg_bonus": "0.00%", "echo_aero_dmg_bonus": "0.00%", "echo_spectro_dmg_bonus": "0.00%", "echo_havoc_dmg_bonus": "0.00%"}, "[20有效-小Ｏ] +0布蘭特+1不滅航路 4攻3共效3共效1攻1攻": {"resonator_src": "/assets/resonator/icon/布蘭特.png", "element": "熱熔", "element_src": "/assets/element/icon/熱熔.png", "element_en": "fusion", "name": "布蘭特", "chain": "0", "weapon_name": "不滅航路", "weapon_rank": "1", "weapon_level": "90", "level": "90", "hp": "16,235.00", "attack": "2,328.62", "defense": "1,307.00", "crit_rate": "63.00%", "crit_dmg": "234.00%", "energy_regen": "241.00%", "resonance_skill_dmg_bonus": "12.00%", "basic_attack_dmg_bonus": "0.00%", "heavy_attack_dmg_bonus": "0.00%", "resonance_liberation_dmg_bonus": "0.00%", "healing_bonus": "0.00%", "physical_dmg_bonus": "0.00%", "glacio_dmg_bonus": "0.00%", "fusion_dmg_bonus": "37.00%", "electro_dmg_bonus": "0.00%", "aero_dmg_bonus": "0.00%", "spectro_dmg_bonus": "0.00%", "havoc_dmg_bonus": "0.00%", "physical_dmg_res": "0.00%", "glacio_dmg_res": "0.00%", "fusion_dmg_res": "0.00%", "electro_dmg_res": "0.00%", "aero_dmg_res": "0.00%", "spectro_dmg_res": "0.00%", "havoc_dmg_res": "0.00%", "normal_attack_lv": "10", "resonance_skill_lv": "10", "resonance_liberation_lv": "10", "forte_circuit_lv": "10", "intro_skill_lv": "10", "inherent_skill_1": "1", "inherent_skill_2": "1", "echo_hp": "4,560.00", "echo_hp_p": "0.00%", "echo_atk": "550.00", "echo_atk_p": "114.00%", "echo_def": "", "echo_def_p": "0.00%", "echo_crit_rate": "42.00%", "echo_crit_dmg": "84.00%", "echo_energy_regen": "64.00%", "echo_sonata_1": "熔山裂谷", "echo_sonata_2": "熔山裂谷", "echo_sonata_3": "熔山裂谷", "echo_sonata_4": "熔山裂谷", "echo_sonata_5": "熔山裂谷", "echo_resonance_skill_dmg_bonus": "12.00%", "echo_basic_attack_dmg_bonus": "0.00%", "echo_heavy_attack_dmg_bonus": "0.00%", "echo_resonance_liberation_dmg_bonus": "0.00%", "echo_healing_bonus": "0.00%", "echo_glacio_dmg_bonus": "0.00%", "echo_fusion_dmg_bonus": "22.00%", "echo_electro_dmg_bonus": "0.00%", "echo_aero_dmg_bonus": "0.00%", "echo_spectro_dmg_bonus": "0.00%", "echo_havoc_dmg_bonus": "0.00%"}, "[20有效-小Ｏ] +0布蘭特+1不滅航路 4攻3共效3攻1攻1攻": {"resonator_src": "/assets/resonator/icon/布蘭特.png", "element": "熱熔", "element_src": "/assets/element/icon/熱熔.png", "element_en": "fusion", "name": "布蘭特", "chain": "0", "weapon_name": "不滅航路", "weapon_rank": "1", "weapon_level": "90", "level": "90", "hp": "16,235.00", "attack": "2,564.72", "defense": "1,307.00", "crit_rate": "63.00%", "crit_dmg": "234.00%", "energy_regen": "209.00%", "resonance_skill_dmg_bonus": "12.00%", "basic_attack_dmg_bonus": "0.00%", "heavy_attack_dmg_bonus": "0.00%", "resonance_liberation_dmg_bonus": "0.00%", "healing_bonus": "0.00%", "physical_dmg_bonus": "0.00%", "glacio_dmg_bonus": "0.00%", "fusion_dmg_bonus": "37.00%", "electro_dmg_bonus": "0.00%", "aero_dmg_bonus": "0.00%", "spectro_dmg_bonus": "0.00%", "havoc_dmg_bonus": "0.00%", "physical_dmg_res": "0.00%", "glacio_dmg_res": "0.00%", "fusion_dmg_res": "0.00%", "electro_dmg_res": "0.00%", "aero_dmg_res": "0.00%", "spectro_dmg_res": "0.00%", "havoc_dmg_res": "0.00%", "normal_attack_lv": "10", "resonance_skill_lv": "10", "resonance_liberation_lv": "10", "forte_circuit_lv": "10", "intro_skill_lv": "10", "inherent_skill_1": "1", "inherent_skill_2": "1", "echo_hp": "4,560.00", "echo_hp_p": "0.00%", "echo_atk": "550.00", "echo_atk_p": "144.00%", "echo_def": "", "echo_def_p": "0.00%", "echo_crit_rate": "42.00%", "echo_crit_dmg": "84.00%", "echo_energy_regen": "32.00%", "echo_sonata_1": "熔山裂谷", "echo_sonata_2": "熔山裂谷", "echo_sonata_3": "熔山裂谷", "echo_sonata_4": "熔山裂谷", "echo_sonata_5": "熔山裂谷", "echo_resonance_skill_dmg_bonus": "12.00%", "echo_basic_attack_dmg_bonus": "0.00%", "echo_heavy_attack_dmg_bonus": "0.00%", "echo_resonance_liberation_dmg_bonus": "0.00%", "echo_healing_bonus": "0.00%", "echo_glacio_dmg_bonus": "0.00%", "echo_fusion_dmg_bonus": "22.00%", "echo_electro_dmg_bonus": "0.00%", "echo_aero_dmg_bonus": "0.00%", "echo_spectro_dmg_bonus": "0.00%", "echo_havoc_dmg_bonus": "0.00%"}, "[20有效-小Ｏ] +0布蘭特+1不滅航路 4攻3共效3熱熔1攻1攻": {"resonator_src": "/assets/resonator/icon/布蘭特.png", "element": "熱熔", "element_src": "/assets/element/icon/熱熔.png", "element_en": "fusion", "name": "布蘭特", "chain": "0", "weapon_name": "不滅航路", "weapon_rank": "1", "weapon_level": "90", "level": "90", "hp": "16,235.00", "attack": "2,328.62", "defense": "1,307.00", "crit_rate": "63.00%", "crit_dmg": "234.00%", "energy_regen": "209.00%", "resonance_skill_dmg_bonus": "12.00%", "basic_attack_dmg_bonus": "0.00%", "heavy_attack_dmg_bonus": "0.00%", "resonance_liberation_dmg_bonus": "0.00%", "healing_bonus": "0.00%", "physical_dmg_bonus": "0.00%", "glacio_dmg_bonus": "0.00%", "fusion_dmg_bonus": "67.00%", "electro_dmg_bonus": "0.00%", "aero_dmg_bonus": "0.00%", "spectro_dmg_bonus": "0.00%", "havoc_dmg_bonus": "0.00%", "physical_dmg_res": "0.00%", "glacio_dmg_res": "0.00%", "fusion_dmg_res": "0.00%", "electro_dmg_res": "0.00%", "aero_dmg_res": "0.00%", "spectro_dmg_res": "0.00%", "havoc_dmg_res": "0.00%", "normal_attack_lv": "10", "resonance_skill_lv": "10", "resonance_liberation_lv": "10", "forte_circuit_lv": "10", "intro_skill_lv": "10", "inherent_skill_1": "1", "inherent_skill_2": "1", "echo_hp": "4,560.00", "echo_hp_p": "0.00%", "echo_atk": "550.00", "echo_atk_p": "114.00%", "echo_def": "", "echo_def_p": "0.00%", "echo_crit_rate": "42.00%", "echo_crit_dmg": "84.00%", "echo_energy_regen": "32.00%", "echo_sonata_1": "熔山裂谷", "echo_sonata_2": "熔山裂谷", "echo_sonata_3": "熔山裂谷", "echo_sonata_4": "熔山裂谷", "echo_sonata_5": "熔山裂谷", "echo_resonance_skill_dmg_bonus": "12.00%", "echo_basic_attack_dmg_bonus": "0.00%", "echo_heavy_attack_dmg_bonus": "0.00%", "echo_resonance_liberation_dmg_bonus": "0.00%", "echo_healing_bonus": "0.00%", "echo_glacio_dmg_bonus": "0.00%", "echo_fusion_dmg_bonus": "52.00%", "echo_electro_dmg_bonus": "0.00%", "echo_aero_dmg_bonus": "0.00%", "echo_spectro_dmg_bonus": "0.00%", "echo_havoc_dmg_bonus": "0.00%"}}, "damage_distributions": [{"template_id": "[腦測]+0布蘭特+1不滅航路,+6散華+1赫奕流明,+0維里奈+1奇幻變奏-熔山-250共效", "monster_id": "90等抗性20白板", "duration_1": "25", "duration_2": "26", "damage": "851815.2573225347108675461744", "damage_no_crit": "398230.6018338170691292875989", "damage_crit": "931859.6082911319417625329815", "resonators": {"布蘭特": {"resonator_id": "[20有效-小Ｏ] +0布蘭特+1不滅航路 4暴3共效3熱熔1攻1攻", "resonator_name": "布蘭特", "basic": "771137.7355984999153583113459", "heavy": "0.0", "skill": "8379.995204912757530343007917", "liberation": "35638.80806230054275989445911", "intro": "36658.71845682149521899736149", "outro": "0.0", "echo": "0.0", "coordinated_attack": "0.0", "none": "0.0", "normal_attack": "244407.5421302218145034300792", "resonance_skill": "8379.995204912757530343007917", "resonance_liberation": "35638.80806230054275989445911", "intro_skill": "36658.71845682149521899736149", "forte_circuit": "526730.1934682781008548812667", "outro_skill": "0.0", "damage": "851815.2573225347108675461744", "damage_no_crit": "398230.6018338170691292875989", "damage_crit": "931859.6082911319417625329815", "skills": {"為我！": {"id": "為我！", "name": "", "type": "變奏技能", "damage": "36658.71845682149521899736149"}, "空中攻擊第二段長按傷害": {"id": "空中攻擊第二段長按傷害", "name": "", "type": "常態攻擊", "damage": "70280.45713889453134353562006"}, "空中攻擊第二段空翻傷害": {"id": "空中攻擊第二段空翻傷害", "name": "", "type": "常態攻擊", "damage": "32466.89399276537311345646438"}, "下落攻擊傷害": {"id": "下落攻擊傷害", "name": "", "type": "共鳴技能", "damage": "8379.995204912757530343007917"}, "火焰歸亡曲傷害": {"id": "火焰歸亡曲傷害", "name": "", "type": "共鳴回路", "damage": "526730.1934682781008548812667"}, "直到世界盡頭": {"id": "直到世界盡頭", "name": "", "type": "共鳴解放", "damage": "35638.80806230054275989445911"}, "空中攻擊第一段傷害": {"id": "空中攻擊第一段傷害", "name": "", "type": "常態攻擊", "damage": "20144.94544946873956939313984"}, "空中攻擊第一段空翻傷害": {"id": "空中攻擊第一段空翻傷害", "name": "", "type": "常態攻擊", "damage": "14669.88944021198487071240106"}, "空中攻擊第二段傷害": {"id": "空中攻擊第二段傷害", "name": "", "type": "常態攻擊", "damage": "26805.09975820982797678100263"}, "空中攻擊第三段傷害": {"id": "空中攻擊第三段傷害", "name": "", "type": "常態攻擊", "damage": "26226.98640686765318627968337"}, "空中攻擊第三段空翻傷害": {"id": "空中攻擊第三段空翻傷害", "name": "", "type": "常態攻擊", "damage": "14423.13564381936080738786280"}, "空中攻擊第四段傷害": {"id": "空中攻擊第四段傷害", "name": "", "type": "常態攻擊", "damage": "39390.13429998434363588390501"}}}}}, {"template_id": "[腦測]+0布蘭特+1不滅航路,+6散華+1赫奕流明,+0維里奈+1奇幻變奏-熔山-250共效", "monster_id": "90等抗性20白板", "duration_1": "25", "duration_2": "26", "damage": "844806.3987302595304508707125", "damage_no_crit": "398230.6018338170691292875989", "damage_crit": "1107081.073098011452179419525", "resonators": {"布蘭特": {"resonator_id": "[20有效-小Ｏ] +0布蘭特+1不滅航路 4暴傷3共效3熱熔1攻1攻", "resonator_name": "布蘭特", "basic": "764792.7032719297430767282321", "heavy": "0.0", "skill": "8311.043397710109315039577838", "liberation": "35345.56681784215587229551452", "intro": "36357.08524277752218680738787", "outro": "0.0", "echo": "0.0", "coordinated_attack": "0.0", "none": "0.0", "normal_attack": "242396.5216807164830703957783", "resonance_skill": "8311.043397710109315039577838", "resonance_liberation": "35345.56681784215587229551452", "intro_skill": "36357.08524277752218680738787", "forte_circuit": "522396.1815912132600063324539", "outro_skill": "0.0", "damage": "844806.3987302595304508707125", "damage_no_crit": "398230.6018338170691292875989", "damage_crit": "1107081.073098011452179419525", "skills": {"為我！": {"id": "為我！", "name": "", "type": "變奏技能", "damage": "36357.08524277752218680738787"}, "空中攻擊第二段長按傷害": {"id": "空中攻擊第二段長按傷害", "name": "", "type": "常態攻擊", "damage": "69702.17941769558615810026386"}, "空中攻擊第二段空翻傷害": {"id": "空中攻擊第二段空翻傷害", "name": "", "type": "常態攻擊", "damage": "32199.75171400302128232189974"}, "下落攻擊傷害": {"id": "下落攻擊傷害", "name": "", "type": "共鳴技能", "damage": "8311.043397710109315039577838"}, "火焰歸亡曲傷害": {"id": "火焰歸亡曲傷害", "name": "", "type": "共鳴回路", "damage": "522396.1815912132600063324539"}, "直到世界盡頭": {"id": "直到世界盡頭", "name": "", "type": "共鳴解放", "damage": "35345.56681784215587229551452"}, "空中攻擊第一段傷害": {"id": "空中攻擊第一段傷害", "name": "", "type": "常態攻擊", "damage": "19979.18993758905288569920844"}, "空中攻擊第一段空翻傷害": {"id": "空中攻擊第一段空翻傷害", "name": "", "type": "常態攻擊", "damage": "14549.18347754357396200527705"}, "空中攻擊第二段傷害": {"id": "空中攻擊第二段傷害", "name": "", "type": "常態攻擊", "damage": "26584.54353766541798501319261"}, "空中攻擊第三段傷害": {"id": "空中攻擊第三段傷害", "name": "", "type": "常態攻擊", "damage": "26011.18698622208483841688653"}, "空中攻擊第三段空翻傷害": {"id": "空中攻擊第三段空翻傷害", "name": "", "type": "常態攻擊", "damage": "14304.46000691836933931398417"}, "空中攻擊第四段傷害": {"id": "空中攻擊第四段傷害", "name": "", "type": "常態攻擊", "damage": "39066.02660307937661952506596"}}}}}, {"template_id": "[腦測]+0布蘭特+1不滅航路,+6散華+1赫奕流明,+0維里奈+1奇幻變奏-熔山-250共效", "monster_id": "90等抗性20白板", "duration_1": "25", "duration_2": "26", "damage": "789239.6887393947515746701850", "damage_no_crit": "368976.0115658694490765171506", "damage_crit": "863403.8670641345108390501320", "resonators": {"布蘭特": {"resonator_id": "[20有效-小Ｏ] +0布蘭特+1不滅航路 4暴3共效3攻1攻1攻", "resonator_name": "布蘭特", "basic": "715829.2485120336581762532984", "heavy": "0.0", "skill": "7693.314260620932094986807388", "liberation": "32628.90757179964972559366755", "intro": "33088.21839494051157783641161", "outro": "0.0", "echo": "0.0", "coordinated_attack": "0.0", "none": "0.0", "normal_attack": "226403.9115939664941656992086", "resonance_skill": "7693.314260620932094986807388", "resonance_liberation": "32628.90757179964972559366755", "intro_skill": "33088.21839494051157783641161", "forte_circuit": "489425.3369180671640105540898", "outro_skill": "0.0", "damage": "789239.6887393947515746701850", "damage_no_crit": "368976.0115658694490765171506", "damage_crit": "863403.8670641345108390501320", "skills": {"為我！": {"id": "為我！", "name": "", "type": "變奏技能", "damage": "33088.21839494051157783641161"}, "空中攻擊第二段長按傷害": {"id": "空中攻擊第二段長按傷害", "name": "", "type": "常態攻擊", "damage": "64793.58883906389788707124011"}, "空中攻擊第二段空翻傷害": {"id": "空中攻擊第二段空翻傷害", "name": "", "type": "常態攻擊", "damage": "30018.87445670223174142480211"}, "下落攻擊傷害": {"id": "下落攻擊傷害", "name": "", "type": "共鳴技能", "damage": "7693.314260620932094986807388"}, "火焰歸亡曲傷害": {"id": "火焰歸亡曲傷害", "name": "", "type": "共鳴回路", "damage": "489425.3369180671640105540898"}, "直到世界盡頭": {"id": "直到世界盡頭", "name": "", "type": "共鳴解放", "damage": "32628.90757179964972559366755"}, "空中攻擊第一段傷害": {"id": "空中攻擊第一段傷害", "name": "", "type": "常態攻擊", "damage": "18783.79020656788272506596306"}, "空中攻擊第一段空翻傷害": {"id": "空中攻擊第一段空翻傷害", "name": "", "type": "常態攻擊", "damage": "13611.30053802139125593667546"}, "空中攻擊第二段傷害": {"id": "空中攻擊第二段傷害", "name": "", "type": "常態攻擊", "damage": "24870.82607184026993984168865"}, "空中攻擊第三段傷害": {"id": "空中攻擊第三段傷害", "name": "", "type": "常態攻擊", "damage": "24354.42854299737137097625330"}, "空中攻擊第三段空翻傷害": {"id": "空中攻擊第三段空翻傷害", "name": "", "type": "常態攻擊", "damage": "13393.35068673296455408970976"}, "空中攻擊第四段傷害": {"id": "空中攻擊第四段傷害", "name": "", "type": "常態攻擊", "damage": "36577.75225204048469129287599"}}}}}, {"template_id": "[腦測]+0布蘭特+1不滅航路,+6散華+1赫奕流明,+0維里奈+1奇幻變奏-熔山-250共效", "monster_id": "90等抗性20白板", "duration_1": "25", "duration_2": "26", "damage": "782745.7109358354492709234831", "damage_no_crit": "368976.0115658694490765171506", "damage_crit": "1025753.312153117068432717678", "resonators": {"布蘭特": {"resonator_id": "[20有效-小Ｏ] +0布蘭特+1不滅航路 4暴傷3共效3攻1攻1攻", "resonator_name": "布蘭特", "basic": "709939.3023812193559864907654", "heavy": "0.0", "skill": "7630.012563104836534036939314", "liberation": "32360.43222198026036833773088", "intro": "32815.96376953099638205804749", "outro": "0.0", "echo": "0.0", "coordinated_attack": "0.0", "none": "0.0", "normal_attack": "224541.0276089015992160422164", "resonance_skill": "7630.012563104836534036939314", "resonance_liberation": "32360.43222198026036833773088", "intro_skill": "32815.96376953099638205804749", "forte_circuit": "485398.2747723177567704485490", "outro_skill": "0.0", "damage": "782745.7109358354492709234831", "damage_no_crit": "368976.0115658694490765171506", "damage_crit": "1025753.312153117068432717678", "skills": {"為我！": {"id": "為我！", "name": "", "type": "變奏技能", "damage": "32815.96376953099638205804749"}, "空中攻擊第二段長按傷害": {"id": "空中攻擊第二段長按傷害", "name": "", "type": "常態攻擊", "damage": "64260.45786030395183620052771"}, "空中攻擊第二段空翻傷害": {"id": "空中攻擊第二段空翻傷害", "name": "", "type": "常態攻擊", "damage": "29771.87483517910912401055409"}, "下落攻擊傷害": {"id": "下落攻擊傷害", "name": "", "type": "共鳴技能", "damage": "7630.012563104836534036939314"}, "火焰歸亡曲傷害": {"id": "火焰歸亡曲傷害", "name": "", "type": "共鳴回路", "damage": "485398.2747723177567704485490"}, "直到世界盡頭": {"id": "直到世界盡頭", "name": "", "type": "共鳴解放", "damage": "32360.43222198026036833773088"}, "空中攻擊第一段傷害": {"id": "空中攻擊第一段傷害", "name": "", "type": "常態攻擊", "damage": "18629.23447602295764981530343"}, "空中攻擊第一段空翻傷害": {"id": "空中攻擊第一段空翻傷害", "name": "", "type": "常態攻擊", "damage": "13499.30479726908808337730871"}, "空中攻擊第二段傷害": {"id": "空中攻擊第二段傷害", "name": "", "type": "常態攻擊", "damage": "24666.18533370825088844327177"}, "空中攻擊第三段傷害": {"id": "空中攻擊第三段傷害", "name": "", "type": "常態攻擊", "damage": "24154.03679809005312126649077"}, "空中攻擊第三段空翻傷害": {"id": "空中攻擊第三段空翻傷害", "name": "", "type": "常態攻擊", "damage": "13283.14826874021084854881267"}, "空中攻擊第四段傷害": {"id": "空中攻擊第四段傷害", "name": "", "type": "常態攻擊", "damage": "36276.78523958797766437994723"}}}}}, {"template_id": "[腦測]+0布蘭特+1不滅航路,+6散華+1赫奕流明,+0維里奈+1奇幻變奏-熔山-250共效", "monster_id": "90等抗性20白板", "duration_1": "25", "duration_2": "26", "damage": "779827.5202064790404878100265", "damage_no_crit": "422854.0940280224707124010554", "damage_crit": "989478.5800255725814670184698", "resonators": {"布蘭特": {"resonator_id": "[20有效-小Ｏ] +0布蘭特+1不滅航路 4攻3共效3熱熔1攻1攻", "resonator_name": "布蘭特", "basic": "705487.3858350197690608970977", "heavy": "0.0", "skill": "7731.951414133071362532981531", "liberation": "32784.36527228040570870712401", "intro": "33823.81768504579435567282322", "outro": "0.0", "echo": "0.0", "coordinated_attack": "0.0", "none": "0.0", "normal_attack": "223597.7507876975989627440633", "resonance_skill": "7731.951414133071362532981531", "resonance_liberation": "32784.36527228040570870712401", "intro_skill": "33823.81768504579435567282322", "forte_circuit": "481889.6350473221700981530344", "outro_skill": "0.0", "damage": "779827.5202064790404878100265", "damage_no_crit": "422854.0940280224707124010554", "damage_crit": "989478.5800255725814670184698", "skills": {"為我！": {"id": "為我！", "name": "", "type": "變奏技能", "damage": "33823.81768504579435567282322"}, "空中攻擊第二段長按傷害": {"id": "空中攻擊第二段長按傷害", "name": "", "type": "常態攻擊", "damage": "64845.51204067801907841688654"}, "空中攻擊第二段空翻傷害": {"id": "空中攻擊第二段空翻傷害", "name": "", "type": "常態攻擊", "damage": "29770.84818243150767810026386"}, "下落攻擊傷害": {"id": "下落攻擊傷害", "name": "", "type": "共鳴技能", "damage": "7731.951414133071362532981531"}, "火焰歸亡曲傷害": {"id": "火焰歸亡曲傷害", "name": "", "type": "共鳴回路", "damage": "481889.6350473221700981530344"}, "直到世界盡頭": {"id": "直到世界盡頭", "name": "", "type": "共鳴解放", "damage": "32784.36527228040570870712401"}, "空中攻擊第一段傷害": {"id": "空中攻擊第一段傷害", "name": "", "type": "常態攻擊", "damage": "18332.62328406127158332453826"}, "空中攻擊第一段空翻傷害": {"id": "空中攻擊第一段空翻傷害", "name": "", "type": "常態攻擊", "damage": "13350.12583681765197783641161"}, "空中攻擊第二段傷害": {"id": "空中攻擊第二段傷害", "name": "", "type": "常態攻擊", "damage": "24393.60271248101142459102902"}, "空中攻擊第三段傷害": {"id": "空中攻擊第三段傷害", "name": "", "type": "常態攻擊", "damage": "23888.97221191923491335092348"}, "空中攻擊第三段空翻傷害": {"id": "空中攻擊第三段空翻傷害", "name": "", "type": "常態攻擊", "damage": "13137.37999702930354511873351"}, "空中攻擊第四段傷害": {"id": "空中攻擊第四段傷害", "name": "", "type": "常態攻擊", "damage": "35878.68652227959876200527704"}}}}}, {"template_id": "[腦測]+0布蘭特+1不滅航路,+6散華+1赫奕流明,+0維里奈+1奇幻變奏-熔山-250共效", "monster_id": "90等抗性20白板", "duration_1": "25", "duration_2": "26", "damage": "747268.1041070021797329815306", "damage_no_crit": "349353.9523641898923482849603", "damage_crit": "817488.2485322043480949868075", "resonators": {"布蘭特": {"resonator_id": "[20有效-小Ｏ] +0布蘭特+1不滅航路 4暴3共效3共效1攻1攻", "resonator_name": "布蘭特", "basic": "678174.9067146071662290237469", "heavy": "0.0", "skill": "7232.050656294571567282321901", "liberation": "30756.77956061553690237467018", "intro": "31104.36717548490503430079156", "outro": "0.0", "echo": "0.0", "coordinated_attack": "0.0", "none": "0.0", "normal_attack": "214502.1374451783920865435357", "resonance_skill": "7232.050656294571567282321901", "resonance_liberation": "30756.77956061553690237467018", "intro_skill": "31104.36717548490503430079156", "forte_circuit": "463672.7692694287741424802112", "outro_skill": "0.0", "damage": "747268.1041070021797329815306", "damage_no_crit": "349353.9523641898923482849603", "damage_crit": "817488.2485322043480949868075", "skills": {"為我！": {"id": "為我！", "name": "", "type": "變奏技能", "damage": "31104.36717548490503430079156"}, "空中攻擊第二段長按傷害": {"id": "空中攻擊第二段長按傷害", "name": "", "type": "常態攻擊", "damage": "60908.79701688053273667546174"}, "空中攻擊第二段空翻傷害": {"id": "空中攻擊第二段空翻傷害", "name": "", "type": "常態攻擊", "damage": "28381.28546004301116094986808"}, "下落攻擊傷害": {"id": "下落攻擊傷害", "name": "", "type": "共鳴技能", "damage": "7232.050656294571567282321901"}, "火焰歸亡曲傷害": {"id": "火焰歸亡曲傷害", "name": "", "type": "共鳴回路", "damage": "463672.7692694287741424802112"}, "直到世界盡頭": {"id": "直到世界盡頭", "name": "", "type": "共鳴解放", "damage": "30756.77956061553690237467018"}, "空中攻擊第一段傷害": {"id": "空中攻擊第一段傷害", "name": "", "type": "常態攻擊", "damage": "17881.46843267449916833773086"}, "空中攻擊第一段空翻傷害": {"id": "空中攻擊第一段空翻傷害", "name": "", "type": "常態攻擊", "damage": "12957.45098415611115039577837"}, "空中攻擊第二段傷害": {"id": "空中攻擊第二段傷害", "name": "", "type": "常態攻擊", "damage": "23676.09978643436167598944593"}, "空中攻擊第三段傷害": {"id": "空中攻擊第三段傷害", "name": "", "type": "常態攻擊", "damage": "23165.47048388699328126649076"}, "空中攻擊第三段空翻傷害": {"id": "空中攻擊第三段空翻傷害", "name": "", "type": "常態攻擊", "damage": "12739.50113286768444854881267"}, "空中攻擊第四段傷害": {"id": "空中攻擊第四段傷害", "name": "", "type": "常態攻擊", "damage": "34792.06414823519846437994722"}}}}}, {"template_id": "[腦測]+0布蘭特+1不滅航路,+6散華+1赫奕流明,+0維里奈+1奇幻變奏-熔山-250共效", "monster_id": "90等抗性20白板", "duration_1": "25", "duration_2": "26", "damage": "741119.4745453924376276517153", "damage_no_crit": "349353.9523641898923482849603", "damage_crit": "971203.9875724479007282321900", "resonators": {"布蘭特": {"resonator_id": "[20有效-小Ｏ] +0布蘭特+1不滅航路 4暴傷3共效3共效1攻1攻", "resonator_name": "布蘭特", "basic": "672594.7859300456486387335095", "heavy": "0.0", "skill": "7172.544302133382011609498682", "liberation": "30503.70834964460027335092348", "intro": "30848.43596356880670395778364", "outro": "0.0", "echo": "0.0", "coordinated_attack": "0.0", "none": "0.0", "normal_attack": "212737.1829715761762376781004", "resonance_skill": "7172.544302133382011609498682", "resonance_liberation": "30503.70834964460027335092348", "intro_skill": "30848.43596356880670395778364", "forte_circuit": "459857.6029584694724010554091", "outro_skill": "0.0", "damage": "741119.4745453924376276517153", "damage_no_crit": "349353.9523641898923482849603", "damage_crit": "971203.9875724479007282321900", "skills": {"為我！": {"id": "為我！", "name": "", "type": "變奏技能", "damage": "30848.43596356880670395778364"}, "空中攻擊第二段長按傷害": {"id": "空中攻擊第二段長按傷害", "name": "", "type": "常態攻擊", "damage": "60407.63066461447505730870712"}, "空中攻擊第二段空翻傷害": {"id": "空中攻擊第二段空翻傷害", "name": "", "type": "常態攻擊", "damage": "28147.76015658496674934036939"}, "下落攻擊傷害": {"id": "下落攻擊傷害", "name": "", "type": "共鳴技能", "damage": "7172.544302133382011609498682"}, "火焰歸亡曲傷害": {"id": "火焰歸亡曲傷害", "name": "", "type": "共鳴回路", "damage": "459857.6029584694724010554091"}, "直到世界盡頭": {"id": "直到世界盡頭", "name": "", "type": "共鳴解放", "damage": "30503.70834964460027335092348"}, "空中攻擊第一段傷害": {"id": "空中攻擊第一段傷害", "name": "", "type": "常態攻擊", "damage": "17734.33713561275480865435356"}, "空中攻擊第一段空翻傷害": {"id": "空中攻擊第一段空翻傷害", "name": "", "type": "常態攻擊", "damage": "12850.83521168245637889182058"}, "空中攻擊第二段傷害": {"id": "空中攻擊第二段傷害", "name": "", "type": "常態攻擊", "damage": "23481.28942821031082722955147"}, "空中攻擊第三段傷害": {"id": "空中攻擊第三段傷害", "name": "", "type": "常態攻擊", "damage": "22974.86165709110217245382586"}, "空中攻擊第三段空翻傷害": {"id": "空中攻擊第三段空翻傷害", "name": "", "type": "常態攻擊", "damage": "12634.67868315357914406332454"}, "空中攻擊第四段傷害": {"id": "空中攻擊第四段傷害", "name": "", "type": "常態攻擊", "damage": "34505.79003462653109973614775"}}}}}, {"template_id": "[腦測]+0布蘭特+1不滅航路,+6散華+1赫奕流明,+0維里奈+1奇幻變奏-熔山-250共效", "monster_id": "90等抗性20白板", "duration_1": "25", "duration_2": "26", "damage": "720271.2622674876203569393141", "damage_no_crit": "390560.2766877169614775725594", "damage_crit": "913911.0474492576898575197889", "resonators": {"布蘭特": {"resonator_id": "[20有效-小Ｏ] +0布蘭特+1不滅航路 4攻3共效3攻1攻1攻", "resonator_name": "布蘭特", "basic": "652883.8947933556813944063325", "heavy": "0.0", "skill": "7070.471590671184882321899736", "liberation": "29907.46501634466057941952507", "intro": "30409.43086711609350079155673", "outro": "0.0", "echo": "0.0", "coordinated_attack": "0.0", "none": "0.0", "normal_attack": "206488.2051590965536139313984", "resonance_skill": "7070.471590671184882321899736", "resonance_liberation": "29907.46501634466057941952507", "intro_skill": "30409.43086711609350079155673", "forte_circuit": "446395.6896342591277804749341", "outro_skill": "0.0", "damage": "720271.2622674876203569393141", "damage_no_crit": "390560.2766877169614775725594", "damage_crit": "913911.0474492576898575197889", "skills": {"為我！": {"id": "為我！", "name": "", "type": "變奏技能", "damage": "30409.43086711609350079155673"}, "空中攻擊第二段長按傷害": {"id": "空中攻擊第二段長按傷害", "name": "", "type": "常態攻擊", "damage": "59547.96770608660995546174143"}, "空中攻擊第二段空翻傷害": {"id": "空中攻擊第二段空翻傷害", "name": "", "type": "常態攻擊", "damage": "27434.71438216600459630606860"}, "下落攻擊傷害": {"id": "下落攻擊傷害", "name": "", "type": "共鳴技能", "damage": "7070.471590671184882321899736"}, "火焰歸亡曲傷害": {"id": "火焰歸亡曲傷害", "name": "", "type": "共鳴回路", "damage": "446395.6896342591277804749341"}, "直到世界盡頭": {"id": "直到世界盡頭", "name": "", "type": "共鳴解放", "damage": "29907.46501634466057941952507"}, "空中攻擊第一段傷害": {"id": "空中攻擊第一段傷害", "name": "", "type": "常態攻擊", "damage": "17050.74048429550494269129288"}, "空中攻擊第一段空翻傷害": {"id": "空中攻擊第一段空翻傷害", "name": "", "type": "常態攻擊", "damage": "12355.48047413802444221635884"}, "空中攻擊第二段傷害": {"id": "空中攻擊第二段傷害", "name": "", "type": "常態攻擊", "damage": "22576.16787227113578554089709"}, "空中攻擊第三段傷害": {"id": "空中攻擊第三段傷害", "name": "", "type": "常態攻擊", "damage": "22125.47041461816151598944593"}, "空中攻擊第三段空翻傷害": {"id": "空中攻擊第三段空翻傷害", "name": "", "type": "常態攻擊", "damage": "12167.56877907205131292875989"}, "空中攻擊第四段傷害": {"id": "空中攻擊第四段傷害", "name": "", "type": "常態攻擊", "damage": "33230.09504644906106279683379"}}}}}, {"template_id": "[腦測]+0布蘭特+1不滅航路,+6散華+1赫奕流明,+0維里奈+1奇幻變奏-熔山-250共效", "monster_id": "90等抗性20白板", "duration_1": "25", "duration_2": "26", "damage": "684084.2606877501818387335095", "damage_no_crit": "370938.2174860374047493403694", "damage_crit": "867995.4289173275271134564645", "resonators": {"布蘭特": {"resonator_id": "[20有效-小Ｏ] +0布蘭特+1不滅航路 4攻3共效3共效1攻1攻", "resonator_name": "布蘭特", "basic": "620419.1275456633314883377311", "heavy": "0.0", "skill": "6672.779987539499943007915567", "liberation": "28293.35633087213095408970976", "intro": "28698.99682367521945329815303", "outro": "0.0", "echo": "0.0", "coordinated_attack": "0.0", "none": "0.0", "normal_attack": "196226.7503273083264730343009", "resonance_skill": "6672.779987539499943007915567", "resonance_liberation": "28293.35633087213095408970976", "intro_skill": "28698.99682367521945329815303", "forte_circuit": "424192.3772183550050153034302", "outro_skill": "0.0", "damage": "684084.2606877501818387335095", "damage_no_crit": "370938.2174860374047493403694", "damage_crit": "867995.4289173275271134564645", "skills": {"為我！": {"id": "為我！", "name": "", "type": "變奏技能", "damage": "28698.99682367521945329815303"}, "空中攻擊第二段長按傷害": {"id": "空中攻擊第二段長按傷害", "name": "", "type": "常態攻擊", "damage": "56198.58337767587502775725594"}, "空中攻擊第二段空翻傷害": {"id": "空中攻擊第二段空翻傷害", "name": "", "type": "常態攻擊", "damage": "26022.82021309684396306068602"}, "下落攻擊傷害": {"id": "下落攻擊傷害", "name": "", "type": "共鳴技能", "damage": "6672.779987539499943007915567"}, "火焰歸亡曲傷害": {"id": "火焰歸亡曲傷害", "name": "", "type": "共鳴回路", "damage": "424192.3772183550050153034302"}, "直到世界盡頭": {"id": "直到世界盡頭", "name": "", "type": "共鳴解放", "damage": "28293.35633087213095408970976"}, "空中攻擊第一段傷害": {"id": "空中攻擊第一段傷害", "name": "", "type": "常態攻擊", "damage": "16272.77797124539837171503958"}, "空中攻擊第一段空翻傷害": {"id": "空中攻擊第一段空翻傷害", "name": "", "type": "常態攻擊", "damage": "11791.74538894010505435356201"}, "空中攻擊第二段傷害": {"id": "空中攻擊第二段傷害", "name": "", "type": "常態攻擊", "damage": "21546.10045032369491588390502"}, "空中攻擊第三段傷害": {"id": "空中攻擊第三段傷害", "name": "", "type": "常態攻擊", "damage": "21100.37623387418803630606860"}, "空中攻擊第三段空翻傷害": {"id": "空中攻擊第三段空翻傷害", "name": "", "type": "常態攻擊", "damage": "11603.83369387413192506596306"}, "空中攻擊第四段傷害": {"id": "空中攻擊第四段傷害", "name": "", "type": "常態攻擊", "damage": "31690.51299827808917889182058"}}}}}]}